{"1":{"1":{"orig_en":"Mui Wo Ferry Pier","dest_en":"Tai O","orig_tc":"梅窩碼頭","dest_tc":"大澳","service_type":"Normal","stops":[{"seq":"1","stop":"1","fare":"12.7","fareHoliday":"21.4"},{"seq":"2","stop":"2","fare":"12.7","fareHoliday":"21.4"},{"seq":"3","stop":"3","fare":"12.7","fareHoliday":"21.4"},{"seq":"4","stop":"4","fare":"12.7","fareHoliday":"21.4"},{"seq":"5","stop":"5","fare":"12.7","fareHoliday":"21.4"},{"seq":"6","stop":"6","fare":"12.7","fareHoliday":"21.4"},{"seq":"7","stop":"7","fare":"12.7","fareHoliday":"21.4"},{"seq":"8","stop":"8","fare":"12.7","fareHoliday":"21.4"},{"seq":"9","stop":"9","fare":"12.7","fareHoliday":"21.4"},{"seq":"10","stop":"10","fare":"12.7","fareHoliday":"21.4"},{"seq":"11","stop":"11","fare":"11.9","fareHoliday":"20.0"},{"seq":"12","stop":"12","fare":"11.9","fareHoliday":"20.0"},{"seq":"13","stop":"13","fare":"11.9","fareHoliday":"20.0"},{"seq":"14","stop":"14","fare":"11.9","fareHoliday":"20.0"},{"seq":"15","stop":"15","fare":"11.9","fareHoliday":"20.0"},{"seq":"16","stop":"16","fare":"9.4","fareHoliday":"16.3"},{"seq":"17","stop":"17","fare":"9.4","fareHoliday":"16.3"},{"seq":"18","stop":"18","fare":"9.4","fareHoliday":"16.3"},{"seq":"19","stop":"83","fare":"9.4","fareHoliday":"16.3"},{"seq":"20","stop":"19","fare":"9.4","fareHoliday":"16.3"},{"seq":"21","stop":"20","fare":"9.4","fareHoliday":"16.3"},{"seq":"22","stop":"21","fare":"9.4","fareHoliday":"16.3"},{"seq":"23","stop":"22","fare":"9.4","fareHoliday":"16.3"},{"seq":"24","stop":"23","fare":"9.4","fareHoliday":"16.3"},{"seq":"25","stop":"24","fare":"9.4","fareHoliday":"16.3"},{"seq":"26","stop":"25","fare":"9.4","fareHoliday":"16.3"},{"seq":"27","stop":"26","fare":"9.4","fareHoliday":"16.3"},{"seq":"28","stop":"27","fare":"6.6","fareHoliday":"13.0"},{"seq":"29","stop":"28","fare":"6.6","fareHoliday":"13.0"},{"seq":"30","stop":"32","fare":"6.6","fareHoliday":"13.0"},{"seq":"31","stop":"30","fare":"6.6","fareHoliday":"13.0"},{"seq":"32","stop":"31","fare":"6.6","fareHoliday":"13.0"},{"seq":"33","stop":"178","fare":"6.6","fareHoliday":"13.0"},{"seq":"34","stop":"33","fare":"6.6","fareHoliday":"13.0"},{"seq":"35","stop":"34","fare":"6.6","fareHoliday":"13.0"},{"seq":"36","stop":"35","fare":"6.6","fareHoliday":"13.0"},{"seq":"37","stop":"36","fare":"6.6","fareHoliday":"13.0"},{"seq":"38","stop":"37","fare":"6.6","fareHoliday":"13.0"},{"seq":"39","stop":"38","fare":"6.6","fareHoliday":"13.0"},{"seq":"40","stop":"39","fare":"5.0","fareHoliday":"7.4"},{"seq":"41","stop":"40","fare":"5.0","fareHoliday":"7.4"},{"seq":"42","stop":"41","fare":"5.0","fareHoliday":"7.4"},{"seq":"43","stop":"42","fare":"5.0","fareHoliday":"7.4"},{"seq":"44","stop":"58","fare":"2.8","fareHoliday":"5.6"},{"seq":"45","stop":"44","fare":"2.8","fareHoliday":"5.6"},{"seq":"46","stop":"45","fare":"2.8","fareHoliday":"5.6"},{"seq":"47","stop":"46","fare":"2.8","fareHoliday":"5.6"},{"seq":"48","stop":"47","fare":"2.8","fareHoliday":"5.6"},{"seq":"49","stop":"48","fare":"2.8","fareHoliday":"5.6"},{"seq":"50","stop":"49","fare":"2.8","fareHoliday":"5.6"},{"seq":"51","stop":"84","fare":"2.8","fareHoliday":"5.6"},{"seq":"52","stop":"51","fare":"2.8","fareHoliday":"5.6"},{"seq":"53","stop":"52","fare":"2.8","fareHoliday":"5.6"},{"seq":"54","stop":"53","fare":"2.8","fareHoliday":"5.6"},{"seq":"55","stop":"54","fare":"2.8","fareHoliday":"5.6"},{"seq":"56","stop":"55","fare":"0.0","fareHoliday":"0.0"}]},"2":{"orig_en":"Tai O","dest_en":"Mui Wo Ferry Pier","orig_tc":"大澳","dest_tc":"梅窩碼頭","service_type":"Normal","stops":[{"seq":"1","stop":"221","fare":"12.7","fareHoliday":"21.4"},{"seq":"2","stop":"222","fare":"12.7","fareHoliday":"21.4"},{"seq":"3","stop":"224","fare":"12.7","fareHoliday":"21.4"},{"seq":"4","stop":"225","fare":"12.7","fareHoliday":"21.4"},{"seq":"5","stop":"226","fare":"12.7","fareHoliday":"21.4"},{"seq":"6","stop":"227","fare":"12.7","fareHoliday":"21.4"},{"seq":"7","stop":"228","fare":"12.7","fareHoliday":"21.4"},{"seq":"8","stop":"229","fare":"11.9","fareHoliday":"20.0"},{"seq":"9","stop":"230","fare":"11.9","fareHoliday":"20.0"},{"seq":"10","stop":"232","fare":"11.9","fareHoliday":"20.0"},{"seq":"11","stop":"233","fare":"11.9","fareHoliday":"20.0"},{"seq":"12","stop":"234","fare":"9.4","fareHoliday":"16.3"},{"seq":"13","stop":"235","fare":"9.4","fareHoliday":"16.3"},{"seq":"14","stop":"40","fare":"9.4","fareHoliday":"16.3"},{"seq":"15","stop":"236","fare":"9.4","fareHoliday":"16.3"},{"seq":"16","stop":"237","fare":"6.6","fareHoliday":"13.0"},{"seq":"17","stop":"238","fare":"6.6","fareHoliday":"13.0"},{"seq":"18","stop":"239","fare":"6.6","fareHoliday":"13.0"},{"seq":"19","stop":"240","fare":"6.6","fareHoliday":"13.0"},{"seq":"20","stop":"241","fare":"6.6","fareHoliday":"13.0"},{"seq":"21","stop":"242","fare":"6.6","fareHoliday":"13.0"},{"seq":"22","stop":"243","fare":"6.6","fareHoliday":"13.0"},{"seq":"23","stop":"244","fare":"6.6","fareHoliday":"13.0"},{"seq":"24","stop":"245","fare":"6.6","fareHoliday":"13.0"},{"seq":"25","stop":"246","fare":"6.6","fareHoliday":"13.0"},{"seq":"26","stop":"247","fare":"6.6","fareHoliday":"13.0"},{"seq":"27","stop":"248","fare":"6.6","fareHoliday":"13.0"},{"seq":"28","stop":"249","fare":"5.0","fareHoliday":"7.4"},{"seq":"29","stop":"250","fare":"5.0","fareHoliday":"7.4"},{"seq":"30","stop":"251","fare":"5.0","fareHoliday":"7.4"},{"seq":"31","stop":"252","fare":"5.0","fareHoliday":"7.4"},{"seq":"32","stop":"253","fare":"5.0","fareHoliday":"7.4"},{"seq":"33","stop":"254","fare":"5.0","fareHoliday":"7.4"},{"seq":"34","stop":"255","fare":"5.0","fareHoliday":"7.4"},{"seq":"35","stop":"256","fare":"5.0","fareHoliday":"7.4"},{"seq":"36","stop":"257","fare":"5.0","fareHoliday":"7.4"},{"seq":"37","stop":"258","fare":"5.0","fareHoliday":"7.4"},{"seq":"38","stop":"259","fare":"3.7","fareHoliday":"6.1"},{"seq":"39","stop":"260","fare":"3.7","fareHoliday":"6.1"},{"seq":"40","stop":"261","fare":"3.7","fareHoliday":"6.1"},{"seq":"41","stop":"262","fare":"3.7","fareHoliday":"6.1"},{"seq":"42","stop":"263","fare":"2.8","fareHoliday":"5.6"},{"seq":"43","stop":"264","fare":"2.8","fareHoliday":"5.6"},{"seq":"44","stop":"265","fare":"2.8","fareHoliday":"5.6"},{"seq":"45","stop":"56","fare":"2.8","fareHoliday":"5.6"},{"seq":"46","stop":"266","fare":"2.8","fareHoliday":"5.6"},{"seq":"47","stop":"57","fare":"2.8","fareHoliday":"5.6"},{"seq":"48","stop":"2","fare":"2.8","fareHoliday":"5.6"},{"seq":"49","stop":"3","fare":"2.8","fareHoliday":"5.6"},{"seq":"50","stop":"4","fare":"2.8","fareHoliday":"5.6"},{"seq":"51","stop":"5","fare":"2.8","fareHoliday":"5.6"},{"seq":"52","stop":"305","fare":"0.0","fareHoliday":"0.0"}]}},"1R":{"3":{"orig_en":"Hung Hom (Hung Luen Road)","dest_en":"Ngong Ping","orig_tc":"紅磡 (紅鸞道)","dest_tc":"昂坪","service_type":"Normal","stops":[{"seq":"1","stop":"127","fare":"0.0","fareHoliday":"56.5"},{"seq":"2","stop":"128","fare":"0.0","fareHoliday":"56.5"},{"seq":"3","stop":"129","fare":"0.0","fareHoliday":"56.5"},{"seq":"4","stop":"183","fare":"0.0","fareHoliday":"56.5"},{"seq":"5","stop":"131","fare":"0.0","fareHoliday":"56.5"},{"seq":"6","stop":"132","fare":"0.0","fareHoliday":"56.5"},{"seq":"7","stop":"184","fare":"0.0","fareHoliday":"56.5"},{"seq":"8","stop":"317","fare":"0.0","fareHoliday":"37.1"},{"seq":"9","stop":"28","fare":"0.0","fareHoliday":"37.1"},{"seq":"10","stop":"62","fare":"0.0","fareHoliday":"0.0"}]}},"2":{"4":{"orig_en":"Mui Wo Ferry Pier","dest_en":"Ngong Ping","orig_tc":"梅窩碼頭","dest_tc":"昂坪","service_type":"Normal","stops":[{"seq":"1","stop":"1","fare":"20.4","fareHoliday":"37.0"},{"seq":"2","stop":"6","fare":"20.4","fareHoliday":"37.0"},{"seq":"3","stop":"7","fare":"20.4","fareHoliday":"37.0"},{"seq":"4","stop":"8","fare":"20.4","fareHoliday":"37.0"},{"seq":"5","stop":"9","fare":"20.4","fareHoliday":"37.0"},{"seq":"6","stop":"10","fare":"20.4","fareHoliday":"37.0"},{"seq":"7","stop":"11","fare":"20.4","fareHoliday":"37.0"},{"seq":"8","stop":"12","fare":"20.4","fareHoliday":"37.0"},{"seq":"9","stop":"13","fare":"20.4","fareHoliday":"37.0"},{"seq":"10","stop":"14","fare":"20.4","fareHoliday":"37.0"},{"seq":"11","stop":"15","fare":"20.4","fareHoliday":"37.0"},{"seq":"12","stop":"16","fare":"20.4","fareHoliday":"37.0"},{"seq":"13","stop":"17","fare":"20.4","fareHoliday":"37.0"},{"seq":"14","stop":"18","fare":"20.4","fareHoliday":"37.0"},{"seq":"15","stop":"83","fare":"20.4","fareHoliday":"37.0"},{"seq":"16","stop":"19","fare":"20.4","fareHoliday":"37.0"},{"seq":"17","stop":"20","fare":"20.4","fareHoliday":"37.0"},{"seq":"18","stop":"21","fare":"20.4","fareHoliday":"37.0"},{"seq":"19","stop":"22","fare":"20.4","fareHoliday":"37.0"},{"seq":"20","stop":"23","fare":"20.4","fareHoliday":"37.0"},{"seq":"21","stop":"24","fare":"20.4","fareHoliday":"37.0"},{"seq":"22","stop":"25","fare":"20.4","fareHoliday":"37.0"},{"seq":"23","stop":"26","fare":"20.4","fareHoliday":"37.0"},{"seq":"24","stop":"27","fare":"13.3","fareHoliday":"25.3"},{"seq":"25","stop":"28","fare":"13.3","fareHoliday":"25.3"},{"seq":"26","stop":"31","fare":"13.3","fareHoliday":"25.3"},{"seq":"27","stop":"178","fare":"13.3","fareHoliday":"25.3"},{"seq":"28","stop":"33","fare":"13.3","fareHoliday":"25.3"},{"seq":"29","stop":"34","fare":"13.3","fareHoliday":"25.3"},{"seq":"30","stop":"35","fare":"13.3","fareHoliday":"25.3"},{"seq":"31","stop":"36","fare":"13.3","fareHoliday":"25.3"},{"seq":"32","stop":"37","fare":"13.3","fareHoliday":"25.3"},{"seq":"33","stop":"38","fare":"13.3","fareHoliday":"25.3"},{"seq":"34","stop":"39","fare":"9.2","fareHoliday":"19.2"},{"seq":"35","stop":"41","fare":"9.2","fareHoliday":"19.2"},{"seq":"36","stop":"42","fare":"9.2","fareHoliday":"19.2"},{"seq":"37","stop":"269","fare":"5.6","fareHoliday":"12.6"},{"seq":"38","stop":"59","fare":"5.6","fareHoliday":"12.6"},{"seq":"39","stop":"62","fare":"0.0","fareHoliday":"0.0"}]},"5":{"orig_en":"Ngong Ping","dest_en":"Mui Wo Ferry Pier","orig_tc":"昂坪","dest_tc":"梅窩碼頭","service_type":"Normal","stops":[{"seq":"1","stop":"270","fare":"20.4","fareHoliday":"37.0"},{"seq":"2","stop":"271","fare":"20.4","fareHoliday":"37.0"},{"seq":"3","stop":"43","fare":"13.3","fareHoliday":"25.3"},{"seq":"4","stop":"234","fare":"10.9","fareHoliday":"20.5"},{"seq":"5","stop":"235","fare":"10.9","fareHoliday":"20.5"},{"seq":"6","stop":"236","fare":"10.9","fareHoliday":"20.5"},{"seq":"7","stop":"237","fare":"7.3","fareHoliday":"17.0"},{"seq":"8","stop":"238","fare":"7.3","fareHoliday":"17.0"},{"seq":"9","stop":"239","fare":"7.3","fareHoliday":"17.0"},{"seq":"10","stop":"240","fare":"7.3","fareHoliday":"17.0"},{"seq":"11","stop":"241","fare":"7.3","fareHoliday":"17.0"},{"seq":"12","stop":"242","fare":"7.3","fareHoliday":"17.0"},{"seq":"13","stop":"243","fare":"7.3","fareHoliday":"17.0"},{"seq":"14","stop":"244","fare":"7.3","fareHoliday":"17.0"},{"seq":"15","stop":"245","fare":"7.3","fareHoliday":"17.0"},{"seq":"16","stop":"246","fare":"7.3","fareHoliday":"17.0"},{"seq":"17","stop":"247","fare":"7.3","fareHoliday":"17.0"},{"seq":"18","stop":"248","fare":"7.3","fareHoliday":"17.0"},{"seq":"19","stop":"249","fare":"5.6","fareHoliday":"9.3"},{"seq":"20","stop":"250","fare":"5.6","fareHoliday":"9.3"},{"seq":"21","stop":"251","fare":"5.6","fareHoliday":"9.3"},{"seq":"22","stop":"252","fare":"5.6","fareHoliday":"9.3"},{"seq":"23","stop":"253","fare":"5.6","fareHoliday":"9.3"},{"seq":"24","stop":"254","fare":"5.6","fareHoliday":"9.3"},{"seq":"25","stop":"255","fare":"5.6","fareHoliday":"9.3"},{"seq":"26","stop":"256","fare":"5.6","fareHoliday":"9.3"},{"seq":"27","stop":"257","fare":"5.6","fareHoliday":"9.3"},{"seq":"28","stop":"258","fare":"5.6","fareHoliday":"9.3"},{"seq":"29","stop":"259","fare":"4.4","fareHoliday":"7.6"},{"seq":"30","stop":"260","fare":"4.4","fareHoliday":"7.6"},{"seq":"31","stop":"261","fare":"4.4","fareHoliday":"7.6"},{"seq":"32","stop":"262","fare":"4.4","fareHoliday":"7.6"},{"seq":"33","stop":"263","fare":"4.4","fareHoliday":"7.6"},{"seq":"34","stop":"264","fare":"4.4","fareHoliday":"7.6"},{"seq":"35","stop":"265","fare":"4.4","fareHoliday":"7.6"},{"seq":"36","stop":"56","fare":"4.4","fareHoliday":"7.6"},{"seq":"37","stop":"266","fare":"4.4","fareHoliday":"7.6"},{"seq":"38","stop":"57","fare":"4.4","fareHoliday":"7.6"},{"seq":"39","stop":"305","fare":"0.0","fareHoliday":"0.0"}]}},"3M":{"7":{"orig_en":"Mui Wo Ferry Pier","dest_en":"Tung Chung Station Bus Terminus","orig_tc":"梅窩碼頭","dest_tc":"東涌站巴士總站","service_type":"Normal","stops":[{"seq":"1","stop":"1","fare":"12.5","fareHoliday":"19.6"},{"seq":"2","stop":"2","fare":"12.5","fareHoliday":"19.6"},{"seq":"3","stop":"3","fare":"12.5","fareHoliday":"19.6"},{"seq":"4","stop":"4","fare":"12.5","fareHoliday":"19.6"},{"seq":"5","stop":"5","fare":"12.5","fareHoliday":"19.6"},{"seq":"6","stop":"6","fare":"12.5","fareHoliday":"19.6"},{"seq":"7","stop":"7","fare":"12.5","fareHoliday":"19.6"},{"seq":"8","stop":"8","fare":"12.5","fareHoliday":"19.6"},{"seq":"9","stop":"9","fare":"12.5","fareHoliday":"19.6"},{"seq":"10","stop":"10","fare":"12.5","fareHoliday":"19.6"},{"seq":"11","stop":"11","fare":"10.2","fareHoliday":"16.9"},{"seq":"12","stop":"12","fare":"10.2","fareHoliday":"16.9"},{"seq":"13","stop":"13","fare":"10.2","fareHoliday":"16.9"},{"seq":"14","stop":"14","fare":"10.2","fareHoliday":"16.9"},{"seq":"15","stop":"15","fare":"10.2","fareHoliday":"16.9"},{"seq":"16","stop":"16","fare":"7.1","fareHoliday":"14.2"},{"seq":"17","stop":"17","fare":"7.1","fareHoliday":"14.2"},{"seq":"18","stop":"18","fare":"7.1","fareHoliday":"14.2"},{"seq":"19","stop":"179","fare":"7.1","fareHoliday":"14.2"},{"seq":"20","stop":"64","fare":"7.1","fareHoliday":"14.2"},{"seq":"21","stop":"65","fare":"7.1","fareHoliday":"14.2"},{"seq":"22","stop":"66","fare":"7.1","fareHoliday":"14.2"},{"seq":"23","stop":"67","fare":"7.1","fareHoliday":"14.2"},{"seq":"24","stop":"68","fare":"2.8","fareHoliday":"5.6"},{"seq":"25","stop":"69","fare":"2.8","fareHoliday":"5.6"},{"seq":"26","stop":"70","fare":"2.8","fareHoliday":"5.6"},{"seq":"27","stop":"71","fare":"2.8","fareHoliday":"5.6"},{"seq":"28","stop":"72","fare":"2.8","fareHoliday":"5.6"},{"seq":"29","stop":"73","fare":"2.8","fareHoliday":"5.6"},{"seq":"30","stop":"74","fare":"2.8","fareHoliday":"5.6"},{"seq":"31","stop":"185","fare":"2.8","fareHoliday":"5.6"},{"seq":"32","stop":"76","fare":"2.8","fareHoliday":"5.6"},{"seq":"33","stop":"77","fare":"2.8","fareHoliday":"5.6"},{"seq":"34","stop":"78","fare":"2.8","fareHoliday":"5.6"},{"seq":"35","stop":"79","fare":"0.0","fareHoliday":"0.0"}]},"8":{"orig_en":"Mui Wo (from Pui O)","dest_en":"Tung Chung Station Bus Terminus","orig_tc":"梅窩 (貝澳開)","dest_tc":"東涌站巴士總站","service_type":"Normal","stops":[{"seq":"1","stop":"12","fare":"10.2","fareHoliday":"0.0"},{"seq":"2","stop":"13","fare":"10.2","fareHoliday":"0.0"},{"seq":"3","stop":"14","fare":"10.2","fareHoliday":"0.0"},{"seq":"4","stop":"15","fare":"10.2","fareHoliday":"0.0"},{"seq":"5","stop":"16","fare":"7.1","fareHoliday":"0.0"},{"seq":"6","stop":"17","fare":"7.1","fareHoliday":"0.0"},{"seq":"7","stop":"18","fare":"7.1","fareHoliday":"0.0"},{"seq":"8","stop":"179","fare":"7.1","fareHoliday":"0.0"},{"seq":"9","stop":"64","fare":"7.1","fareHoliday":"0.0"},{"seq":"10","stop":"65","fare":"7.1","fareHoliday":"0.0"},{"seq":"11","stop":"66","fare":"7.1","fareHoliday":"0.0"},{"seq":"12","stop":"67","fare":"7.1","fareHoliday":"0.0"},{"seq":"13","stop":"68","fare":"2.8","fareHoliday":"0.0"},{"seq":"14","stop":"69","fare":"2.8","fareHoliday":"0.0"},{"seq":"15","stop":"70","fare":"2.8","fareHoliday":"0.0"},{"seq":"16","stop":"71","fare":"2.8","fareHoliday":"0.0"},{"seq":"17","stop":"72","fare":"2.8","fareHoliday":"0.0"},{"seq":"18","stop":"73","fare":"2.8","fareHoliday":"0.0"},{"seq":"19","stop":"74","fare":"2.8","fareHoliday":"0.0"},{"seq":"20","stop":"77","fare":"2.8","fareHoliday":"0.0"},{"seq":"21","stop":"78","fare":"2.8","fareHoliday":"0.0"},{"seq":"22","stop":"79","fare":"0.0","fareHoliday":"0.0"}]},"6":{"orig_en":"Tung Chung Station Bus Terminus","dest_en":"Mui Wo Ferry Pier","orig_tc":"東涌站巴士總站","dest_tc":"梅窩碼頭","service_type":"Normal","stops":[{"seq":"1","stop":"278","fare":"12.5","fareHoliday":"19.6"},{"seq":"2","stop":"80","fare":"12.5","fareHoliday":"19.6"},{"seq":"3","stop":"81","fare":"12.5","fareHoliday":"19.6"},{"seq":"4","stop":"185","fare":"12.5","fareHoliday":"19.6"},{"seq":"5","stop":"76","fare":"12.5","fareHoliday":"19.6"},{"seq":"6","stop":"338","fare":"12.5","fareHoliday":"19.6"},{"seq":"7","stop":"94","fare":"12.5","fareHoliday":"19.6"},{"seq":"8","stop":"279","fare":"12.5","fareHoliday":"19.6"},{"seq":"9","stop":"280","fare":"12.5","fareHoliday":"19.6"},{"seq":"10","stop":"282","fare":"12.5","fareHoliday":"19.6"},{"seq":"11","stop":"283","fare":"12.5","fareHoliday":"19.6"},{"seq":"12","stop":"284","fare":"12.5","fareHoliday":"19.6"},{"seq":"13","stop":"286","fare":"12.5","fareHoliday":"19.6"},{"seq":"14","stop":"287","fare":"12.5","fareHoliday":"19.6"},{"seq":"15","stop":"288","fare":"12.5","fareHoliday":"19.6"},{"seq":"16","stop":"273","fare":"6.6","fareHoliday":"13.0"},{"seq":"17","stop":"256","fare":"5.0","fareHoliday":"7.4"},{"seq":"18","stop":"257","fare":"5.0","fareHoliday":"7.4"},{"seq":"19","stop":"258","fare":"5.0","fareHoliday":"7.4"},{"seq":"20","stop":"259","fare":"3.7","fareHoliday":"6.1"},{"seq":"21","stop":"260","fare":"3.7","fareHoliday":"6.1"},{"seq":"22","stop":"261","fare":"3.7","fareHoliday":"6.1"},{"seq":"23","stop":"262","fare":"3.7","fareHoliday":"6.1"},{"seq":"24","stop":"263","fare":"3.7","fareHoliday":"6.1"},{"seq":"25","stop":"264","fare":"3.7","fareHoliday":"6.1"},{"seq":"26","stop":"265","fare":"3.7","fareHoliday":"6.1"},{"seq":"27","stop":"56","fare":"3.7","fareHoliday":"6.1"},{"seq":"28","stop":"266","fare":"3.7","fareHoliday":"6.1"},{"seq":"29","stop":"57","fare":"3.7","fareHoliday":"6.1"},{"seq":"30","stop":"2","fare":"3.7","fareHoliday":"6.1"},{"seq":"31","stop":"3","fare":"3.7","fareHoliday":"6.1"},{"seq":"32","stop":"4","fare":"3.7","fareHoliday":"6.1"},{"seq":"33","stop":"5","fare":"3.7","fareHoliday":"6.1"},{"seq":"34","stop":"305","fare":"0.0","fareHoliday":"0.0"}]}},"4":{"11":{"orig_en":"Tong Fuk (from Shui Hau)","dest_en":"Mui Wo Ferry Pier","orig_tc":"塘福 (水口開)","dest_tc":"梅窩碼頭","service_type":"Normal","stops":[{"seq":"1","stop":"240","fare":"6.7","fareHoliday":"13.0"},{"seq":"2","stop":"241","fare":"6.7","fareHoliday":"13.0"},{"seq":"3","stop":"242","fare":"6.7","fareHoliday":"13.0"},{"seq":"4","stop":"243","fare":"6.7","fareHoliday":"13.0"},{"seq":"5","stop":"244","fare":"6.7","fareHoliday":"13.0"},{"seq":"6","stop":"245","fare":"6.7","fareHoliday":"13.0"},{"seq":"7","stop":"246","fare":"6.7","fareHoliday":"13.0"},{"seq":"8","stop":"247","fare":"6.7","fareHoliday":"13.0"},{"seq":"9","stop":"248","fare":"6.7","fareHoliday":"13.0"},{"seq":"10","stop":"249","fare":"5.0","fareHoliday":"7.4"},{"seq":"11","stop":"250","fare":"5.0","fareHoliday":"7.4"},{"seq":"12","stop":"251","fare":"5.0","fareHoliday":"7.4"},{"seq":"13","stop":"252","fare":"5.0","fareHoliday":"7.4"},{"seq":"14","stop":"253","fare":"5.0","fareHoliday":"7.4"},{"seq":"15","stop":"254","fare":"5.0","fareHoliday":"7.4"},{"seq":"16","stop":"255","fare":"5.0","fareHoliday":"7.4"},{"seq":"17","stop":"256","fare":"5.0","fareHoliday":"7.4"},{"seq":"18","stop":"257","fare":"5.0","fareHoliday":"7.4"},{"seq":"19","stop":"258","fare":"5.0","fareHoliday":"7.4"},{"seq":"20","stop":"259","fare":"3.7","fareHoliday":"6.1"},{"seq":"21","stop":"260","fare":"3.7","fareHoliday":"6.1"},{"seq":"22","stop":"261","fare":"3.7","fareHoliday":"6.1"},{"seq":"23","stop":"262","fare":"3.7","fareHoliday":"6.1"},{"seq":"24","stop":"263","fare":"3.7","fareHoliday":"6.1"},{"seq":"25","stop":"264","fare":"3.7","fareHoliday":"6.1"},{"seq":"26","stop":"265","fare":"3.7","fareHoliday":"6.1"},{"seq":"27","stop":"56","fare":"3.7","fareHoliday":"6.1"},{"seq":"28","stop":"266","fare":"3.7","fareHoliday":"6.1"},{"seq":"29","stop":"57","fare":"3.7","fareHoliday":"6.1"},{"seq":"30","stop":"305","fare":"0.0","fareHoliday":"0.0"}]},"12":{"orig_en":"Mui Wo Ferry Pier","dest_en":"Tong Fuk (to Shui Hau)","orig_tc":"梅窩碼頭","dest_tc":"塘福 (至水口)","service_type":"Normal","stops":[{"seq":"1","stop":"1","fare":"6.7","fareHoliday":"13.0"},{"seq":"2","stop":"2","fare":"6.7","fareHoliday":"13.0"},{"seq":"3","stop":"3","fare":"6.7","fareHoliday":"13.0"},{"seq":"4","stop":"4","fare":"6.7","fareHoliday":"13.0"},{"seq":"5","stop":"5","fare":"6.7","fareHoliday":"13.0"},{"seq":"6","stop":"6","fare":"6.7","fareHoliday":"13.0"},{"seq":"7","stop":"7","fare":"6.7","fareHoliday":"13.0"},{"seq":"8","stop":"8","fare":"6.7","fareHoliday":"13.0"},{"seq":"9","stop":"9","fare":"6.7","fareHoliday":"13.0"},{"seq":"10","stop":"10","fare":"6.7","fareHoliday":"13.0"},{"seq":"11","stop":"11","fare":"5.0","fareHoliday":"7.4"},{"seq":"12","stop":"12","fare":"5.0","fareHoliday":"7.4"},{"seq":"13","stop":"13","fare":"5.0","fareHoliday":"7.4"},{"seq":"14","stop":"14","fare":"5.0","fareHoliday":"7.4"},{"seq":"15","stop":"15","fare":"5.0","fareHoliday":"7.4"},{"seq":"16","stop":"16","fare":"5.0","fareHoliday":"7.4"},{"seq":"17","stop":"17","fare":"5.0","fareHoliday":"7.4"},{"seq":"18","stop":"18","fare":"5.0","fareHoliday":"7.4"},{"seq":"19","stop":"83","fare":"5.0","fareHoliday":"7.4"},{"seq":"20","stop":"19","fare":"2.8","fareHoliday":"5.6"},{"seq":"21","stop":"20","fare":"2.8","fareHoliday":"5.6"},{"seq":"22","stop":"21","fare":"2.8","fareHoliday":"5.6"},{"seq":"23","stop":"22","fare":"2.8","fareHoliday":"5.6"},{"seq":"24","stop":"23","fare":"2.8","fareHoliday":"5.6"},{"seq":"25","stop":"24","fare":"2.8","fareHoliday":"5.6"},{"seq":"26","stop":"25","fare":"2.8","fareHoliday":"5.6"},{"seq":"27","stop":"26","fare":"2.8","fareHoliday":"5.6"},{"seq":"28","stop":"27","fare":"2.8","fareHoliday":"5.6"},{"seq":"29","stop":"28","fare":"2.8","fareHoliday":"5.6"},{"seq":"30","stop":"32","fare":"2.8","fareHoliday":"5.6"},{"seq":"31","stop":"30","fare":"2.8","fareHoliday":"5.6"},{"seq":"32","stop":"31","fare":"2.8","fareHoliday":"5.6"},{"seq":"33","stop":"178","fare":"2.8","fareHoliday":"5.6"},{"seq":"34","stop":"33","fare":"2.8","fareHoliday":"5.6"},{"seq":"35","stop":"34","fare":"2.8","fareHoliday":"5.6"},{"seq":"36","stop":"240","fare":"0.0","fareHoliday":"0.0"}]},"10":{"orig_en":"Tong Fuk","dest_en":"Mui Wo Ferry Pier","orig_tc":"塘福","dest_tc":"梅窩碼頭","service_type":"Normal","stops":[{"seq":"1","stop":"181","fare":"6.7","fareHoliday":"13.0"},{"seq":"2","stop":"246","fare":"6.7","fareHoliday":"13.0"},{"seq":"3","stop":"247","fare":"6.7","fareHoliday":"13.0"},{"seq":"4","stop":"248","fare":"6.7","fareHoliday":"13.0"},{"seq":"5","stop":"249","fare":"5.0","fareHoliday":"7.4"},{"seq":"6","stop":"250","fare":"5.0","fareHoliday":"7.4"},{"seq":"7","stop":"251","fare":"5.0","fareHoliday":"7.4"},{"seq":"8","stop":"252","fare":"5.0","fareHoliday":"7.4"},{"seq":"9","stop":"253","fare":"5.0","fareHoliday":"7.4"},{"seq":"10","stop":"254","fare":"5.0","fareHoliday":"7.4"},{"seq":"11","stop":"255","fare":"5.0","fareHoliday":"7.4"},{"seq":"12","stop":"256","fare":"5.0","fareHoliday":"7.4"},{"seq":"13","stop":"257","fare":"5.0","fareHoliday":"7.4"},{"seq":"14","stop":"258","fare":"5.0","fareHoliday":"7.4"},{"seq":"15","stop":"259","fare":"3.7","fareHoliday":"6.1"},{"seq":"16","stop":"260","fare":"3.7","fareHoliday":"6.1"},{"seq":"17","stop":"261","fare":"3.7","fareHoliday":"6.1"},{"seq":"18","stop":"262","fare":"3.7","fareHoliday":"6.1"},{"seq":"19","stop":"263","fare":"3.7","fareHoliday":"6.1"},{"seq":"20","stop":"264","fare":"3.7","fareHoliday":"6.1"},{"seq":"21","stop":"265","fare":"3.7","fareHoliday":"6.1"},{"seq":"22","stop":"56","fare":"3.7","fareHoliday":"6.1"},{"seq":"23","stop":"266","fare":"3.7","fareHoliday":"6.1"},{"seq":"24","stop":"57","fare":"3.7","fareHoliday":"6.1"},{"seq":"25","stop":"2","fare":"3.7","fareHoliday":"6.1"},{"seq":"26","stop":"3","fare":"3.7","fareHoliday":"6.1"},{"seq":"27","stop":"4","fare":"3.7","fareHoliday":"6.1"},{"seq":"28","stop":"5","fare":"3.7","fareHoliday":"6.1"},{"seq":"29","stop":"305","fare":"0.0","fareHoliday":"0.0"}]},"9":{"orig_en":"Mui Wo Ferry Pier","dest_en":"Tong Fuk","orig_tc":"梅窩碼頭","dest_tc":"塘福","service_type":"Normal","stops":[{"seq":"1","stop":"1","fare":"6.7","fareHoliday":"13.0"},{"seq":"2","stop":"6","fare":"6.7","fareHoliday":"13.0"},{"seq":"3","stop":"7","fare":"6.7","fareHoliday":"13.0"},{"seq":"4","stop":"8","fare":"6.7","fareHoliday":"13.0"},{"seq":"5","stop":"9","fare":"6.7","fareHoliday":"13.0"},{"seq":"6","stop":"10","fare":"6.7","fareHoliday":"13.0"},{"seq":"7","stop":"11","fare":"5.0","fareHoliday":"7.4"},{"seq":"8","stop":"12","fare":"5.0","fareHoliday":"7.4"},{"seq":"9","stop":"13","fare":"5.0","fareHoliday":"7.4"},{"seq":"10","stop":"14","fare":"5.0","fareHoliday":"7.4"},{"seq":"11","stop":"15","fare":"5.0","fareHoliday":"7.4"},{"seq":"12","stop":"16","fare":"5.0","fareHoliday":"7.4"},{"seq":"13","stop":"17","fare":"5.0","fareHoliday":"7.4"},{"seq":"14","stop":"18","fare":"5.0","fareHoliday":"7.4"},{"seq":"15","stop":"83","fare":"5.0","fareHoliday":"7.4"},{"seq":"16","stop":"19","fare":"2.8","fareHoliday":"5.6"},{"seq":"17","stop":"20","fare":"2.8","fareHoliday":"5.6"},{"seq":"18","stop":"21","fare":"2.8","fareHoliday":"5.6"},{"seq":"19","stop":"22","fare":"2.8","fareHoliday":"5.6"},{"seq":"20","stop":"23","fare":"2.8","fareHoliday":"5.6"},{"seq":"21","stop":"24","fare":"2.8","fareHoliday":"5.6"},{"seq":"22","stop":"25","fare":"2.8","fareHoliday":"5.6"},{"seq":"23","stop":"26","fare":"2.8","fareHoliday":"5.6"},{"seq":"24","stop":"27","fare":"2.8","fareHoliday":"5.6"},{"seq":"25","stop":"181","fare":"0.0","fareHoliday":"0.0"}]}},"7S":{"72":{"orig_en":"Lai Chi Yuen Cemetery","dest_en":"Mui Wo Ferry Pier","orig_tc":"禮智園墳場","dest_tc":"梅窩碼頭","service_type":"Special","stops":[{"seq":"1","stop":"56","fare":"0.0","fareHoliday":"6.4"},{"seq":"2","stop":"2","fare":"0.0","fareHoliday":"6.4"},{"seq":"3","stop":"3","fare":"0.0","fareHoliday":"6.4"},{"seq":"4","stop":"4","fare":"0.0","fareHoliday":"6.4"},{"seq":"5","stop":"5","fare":"0.0","fareHoliday":"6.4"},{"seq":"6","stop":"305","fare":"0.0","fareHoliday":"0.0"}]},"70":{"orig_en":"Mui Wo Ferry Pier","dest_en":"Lai Chi Yuen Cemetery","orig_tc":"梅窩碼頭","dest_tc":"禮智園墳場","service_type":"Special","stops":[{"seq":"1","stop":"1","fare":"0.0","fareHoliday":"6.4"},{"seq":"2","stop":"2","fare":"0.0","fareHoliday":"6.4"},{"seq":"3","stop":"3","fare":"0.0","fareHoliday":"6.4"},{"seq":"4","stop":"4","fare":"0.0","fareHoliday":"6.4"},{"seq":"5","stop":"5","fare":"0.0","fareHoliday":"6.4"},{"seq":"6","stop":"56","fare":"0.0","fareHoliday":"0.0"}]}},"11":{"13":{"orig_en":"Tung Chung Station Bus Terminus","dest_en":"Tai O","orig_tc":"東涌站巴士總站","dest_tc":"大澳","service_type":"Normal","stops":[{"seq":"1","stop":"278","fare":"14.0","fareHoliday":"23.3"},{"seq":"2","stop":"80","fare":"14.0","fareHoliday":"23.3"},{"seq":"3","stop":"81","fare":"14.0","fareHoliday":"23.3"},{"seq":"4","stop":"185","fare":"14.0","fareHoliday":"23.3"},{"seq":"5","stop":"76","fare":"14.0","fareHoliday":"23.3"},{"seq":"6","stop":"338","fare":"14.0","fareHoliday":"23.3"},{"seq":"7","stop":"94","fare":"14.0","fareHoliday":"23.3"},{"seq":"8","stop":"279","fare":"14.0","fareHoliday":"23.3"},{"seq":"9","stop":"280","fare":"14.0","fareHoliday":"23.3"},{"seq":"10","stop":"282","fare":"14.0","fareHoliday":"23.3"},{"seq":"11","stop":"283","fare":"14.0","fareHoliday":"23.3"},{"seq":"12","stop":"284","fare":"14.0","fareHoliday":"23.3"},{"seq":"13","stop":"286","fare":"14.0","fareHoliday":"23.3"},{"seq":"14","stop":"287","fare":"14.0","fareHoliday":"23.3"},{"seq":"15","stop":"288","fare":"14.0","fareHoliday":"23.3"},{"seq":"16","stop":"273","fare":"14.0","fareHoliday":"23.3"},{"seq":"17","stop":"83","fare":"14.0","fareHoliday":"23.3"},{"seq":"18","stop":"19","fare":"10.1","fareHoliday":"17.6"},{"seq":"19","stop":"20","fare":"10.1","fareHoliday":"17.6"},{"seq":"20","stop":"21","fare":"10.1","fareHoliday":"17.6"},{"seq":"21","stop":"22","fare":"10.1","fareHoliday":"17.6"},{"seq":"22","stop":"23","fare":"10.1","fareHoliday":"17.6"},{"seq":"23","stop":"24","fare":"10.1","fareHoliday":"17.6"},{"seq":"24","stop":"25","fare":"10.1","fareHoliday":"17.6"},{"seq":"25","stop":"26","fare":"10.1","fareHoliday":"17.6"},{"seq":"26","stop":"27","fare":"7.1","fareHoliday":"14.2"},{"seq":"27","stop":"28","fare":"7.1","fareHoliday":"14.2"},{"seq":"28","stop":"32","fare":"7.1","fareHoliday":"14.2"},{"seq":"29","stop":"30","fare":"7.1","fareHoliday":"14.2"},{"seq":"30","stop":"31","fare":"7.1","fareHoliday":"14.2"},{"seq":"31","stop":"178","fare":"7.1","fareHoliday":"14.2"},{"seq":"32","stop":"33","fare":"7.1","fareHoliday":"14.2"},{"seq":"33","stop":"34","fare":"7.1","fareHoliday":"14.2"},{"seq":"34","stop":"35","fare":"7.1","fareHoliday":"14.2"},{"seq":"35","stop":"36","fare":"7.1","fareHoliday":"14.2"},{"seq":"36","stop":"37","fare":"7.1","fareHoliday":"14.2"},{"seq":"37","stop":"38","fare":"7.1","fareHoliday":"14.2"},{"seq":"38","stop":"39","fare":"5.2","fareHoliday":"7.8"},{"seq":"39","stop":"40","fare":"5.2","fareHoliday":"7.8"},{"seq":"40","stop":"41","fare":"5.2","fareHoliday":"7.8"},{"seq":"41","stop":"42","fare":"5.2","fareHoliday":"7.8"},{"seq":"42","stop":"58","fare":"2.8","fareHoliday":"5.6"},{"seq":"43","stop":"44","fare":"2.8","fareHoliday":"5.6"},{"seq":"44","stop":"45","fare":"2.8","fareHoliday":"5.6"},{"seq":"45","stop":"46","fare":"2.8","fareHoliday":"5.6"},{"seq":"46","stop":"47","fare":"2.8","fareHoliday":"5.6"},{"seq":"47","stop":"48","fare":"2.8","fareHoliday":"5.6"},{"seq":"48","stop":"49","fare":"2.8","fareHoliday":"5.6"},{"seq":"49","stop":"84","fare":"2.8","fareHoliday":"5.6"},{"seq":"50","stop":"51","fare":"2.8","fareHoliday":"5.6"},{"seq":"51","stop":"52","fare":"2.8","fareHoliday":"5.6"},{"seq":"52","stop":"53","fare":"2.8","fareHoliday":"5.6"},{"seq":"53","stop":"54","fare":"2.8","fareHoliday":"5.6"},{"seq":"54","stop":"55","fare":"0.0","fareHoliday":"0.0"}]},"18":{"orig_en":"Tai O (from Shui Hau)","dest_en":"Tung Chung Station Bus Terminus","orig_tc":"大澳 (水口開)","dest_tc":"東涌站巴士總站","service_type":"Normal","stops":[{"seq":"1","stop":"240","fare":"7.1","fareHoliday":"14.2"},{"seq":"2","stop":"241","fare":"7.1","fareHoliday":"14.2"},{"seq":"3","stop":"242","fare":"7.1","fareHoliday":"14.2"},{"seq":"4","stop":"243","fare":"7.1","fareHoliday":"14.2"},{"seq":"5","stop":"244","fare":"7.1","fareHoliday":"14.2"},{"seq":"6","stop":"245","fare":"7.1","fareHoliday":"14.2"},{"seq":"7","stop":"246","fare":"7.1","fareHoliday":"14.2"},{"seq":"8","stop":"247","fare":"7.1","fareHoliday":"14.2"},{"seq":"9","stop":"248","fare":"7.1","fareHoliday":"14.2"},{"seq":"10","stop":"249","fare":"7.1","fareHoliday":"14.2"},{"seq":"11","stop":"250","fare":"7.1","fareHoliday":"14.2"},{"seq":"12","stop":"251","fare":"7.1","fareHoliday":"14.2"},{"seq":"13","stop":"252","fare":"7.1","fareHoliday":"14.2"},{"seq":"14","stop":"253","fare":"7.1","fareHoliday":"14.2"},{"seq":"15","stop":"254","fare":"7.1","fareHoliday":"14.2"},{"seq":"16","stop":"255","fare":"7.1","fareHoliday":"14.2"},{"seq":"17","stop":"179","fare":"7.1","fareHoliday":"14.2"},{"seq":"18","stop":"64","fare":"7.1","fareHoliday":"14.2"},{"seq":"19","stop":"65","fare":"7.1","fareHoliday":"14.2"},{"seq":"20","stop":"66","fare":"7.1","fareHoliday":"14.2"},{"seq":"21","stop":"67","fare":"7.1","fareHoliday":"14.2"},{"seq":"22","stop":"68","fare":"2.8","fareHoliday":"5.6"},{"seq":"23","stop":"69","fare":"2.8","fareHoliday":"5.6"},{"seq":"24","stop":"70","fare":"2.8","fareHoliday":"5.6"},{"seq":"25","stop":"71","fare":"2.8","fareHoliday":"5.6"},{"seq":"26","stop":"72","fare":"2.8","fareHoliday":"5.6"},{"seq":"27","stop":"73","fare":"2.8","fareHoliday":"5.6"},{"seq":"28","stop":"74","fare":"2.8","fareHoliday":"5.6"},{"seq":"29","stop":"77","fare":"2.8","fareHoliday":"5.6"},{"seq":"30","stop":"78","fare":"2.8","fareHoliday":"5.6"},{"seq":"31","stop":"79","fare":"0.0","fareHoliday":"0.0"}]},"17":{"orig_en":"Tai O (from Sha Tsui)","dest_en":"Tung Chung Station Bus Terminus","orig_tc":"大澳 (沙咀開)","dest_tc":"東涌站巴士總站","service_type":"Normal","stops":[{"seq":"1","stop":"40","fare":"10.1","fareHoliday":"17.6"},{"seq":"2","stop":"236","fare":"10.1","fareHoliday":"17.6"},{"seq":"3","stop":"237","fare":"7.1","fareHoliday":"14.2"},{"seq":"4","stop":"238","fare":"7.1","fareHoliday":"14.2"},{"seq":"5","stop":"239","fare":"7.1","fareHoliday":"14.2"},{"seq":"6","stop":"240","fare":"7.1","fareHoliday":"14.2"},{"seq":"7","stop":"241","fare":"7.1","fareHoliday":"14.2"},{"seq":"8","stop":"242","fare":"7.1","fareHoliday":"14.2"},{"seq":"9","stop":"243","fare":"7.1","fareHoliday":"14.2"},{"seq":"10","stop":"32","fare":"7.1","fareHoliday":"14.2"},{"seq":"11","stop":"30","fare":"7.1","fareHoliday":"14.2"},{"seq":"12","stop":"244","fare":"7.1","fareHoliday":"14.2"},{"seq":"13","stop":"245","fare":"7.1","fareHoliday":"14.2"},{"seq":"14","stop":"246","fare":"7.1","fareHoliday":"14.2"},{"seq":"15","stop":"247","fare":"7.1","fareHoliday":"14.2"},{"seq":"16","stop":"248","fare":"7.1","fareHoliday":"14.2"},{"seq":"17","stop":"249","fare":"7.1","fareHoliday":"14.2"},{"seq":"18","stop":"250","fare":"7.1","fareHoliday":"14.2"},{"seq":"19","stop":"251","fare":"7.1","fareHoliday":"14.2"},{"seq":"20","stop":"252","fare":"7.1","fareHoliday":"14.2"},{"seq":"21","stop":"253","fare":"7.1","fareHoliday":"14.2"},{"seq":"22","stop":"254","fare":"7.1","fareHoliday":"14.2"},{"seq":"23","stop":"255","fare":"7.1","fareHoliday":"14.2"},{"seq":"24","stop":"179","fare":"7.1","fareHoliday":"14.2"},{"seq":"25","stop":"64","fare":"7.1","fareHoliday":"14.2"},{"seq":"26","stop":"65","fare":"7.1","fareHoliday":"14.2"},{"seq":"27","stop":"66","fare":"7.1","fareHoliday":"14.2"},{"seq":"28","stop":"67","fare":"7.1","fareHoliday":"14.2"},{"seq":"29","stop":"68","fare":"2.8","fareHoliday":"5.6"},{"seq":"30","stop":"69","fare":"2.8","fareHoliday":"5.6"},{"seq":"31","stop":"70","fare":"2.8","fareHoliday":"5.6"},{"seq":"32","stop":"71","fare":"2.8","fareHoliday":"5.6"},{"seq":"33","stop":"72","fare":"2.8","fareHoliday":"5.6"},{"seq":"34","stop":"73","fare":"2.8","fareHoliday":"5.6"},{"seq":"35","stop":"74","fare":"2.8","fareHoliday":"5.6"},{"seq":"36","stop":"77","fare":"2.8","fareHoliday":"5.6"},{"seq":"37","stop":"78","fare":"2.8","fareHoliday":"5.6"},{"seq":"38","stop":"79","fare":"0.0","fareHoliday":"0.0"}]},"14":{"orig_en":"Tai O","dest_en":"Tung Chung Station Bus Terminus","orig_tc":"大澳","dest_tc":"東涌站巴士總站","service_type":"Normal","stops":[{"seq":"1","stop":"221","fare":"14.0","fareHoliday":"23.3"},{"seq":"2","stop":"222","fare":"14.0","fareHoliday":"23.3"},{"seq":"3","stop":"224","fare":"14.0","fareHoliday":"23.3"},{"seq":"4","stop":"225","fare":"14.0","fareHoliday":"23.3"},{"seq":"5","stop":"226","fare":"14.0","fareHoliday":"23.3"},{"seq":"6","stop":"227","fare":"14.0","fareHoliday":"23.3"},{"seq":"7","stop":"228","fare":"14.0","fareHoliday":"23.3"},{"seq":"8","stop":"229","fare":"12.7","fareHoliday":"21.2"},{"seq":"9","stop":"230","fare":"12.7","fareHoliday":"21.2"},{"seq":"10","stop":"232","fare":"12.7","fareHoliday":"21.2"},{"seq":"11","stop":"233","fare":"12.7","fareHoliday":"21.2"},{"seq":"12","stop":"234","fare":"10.1","fareHoliday":"17.6"},{"seq":"13","stop":"235","fare":"10.1","fareHoliday":"17.6"},{"seq":"14","stop":"40","fare":"10.1","fareHoliday":"17.6"},{"seq":"15","stop":"236","fare":"10.1","fareHoliday":"17.6"},{"seq":"16","stop":"237","fare":"7.1","fareHoliday":"14.2"},{"seq":"17","stop":"238","fare":"7.1","fareHoliday":"14.2"},{"seq":"18","stop":"239","fare":"7.1","fareHoliday":"14.2"},{"seq":"19","stop":"240","fare":"7.1","fareHoliday":"14.2"},{"seq":"20","stop":"241","fare":"7.1","fareHoliday":"14.2"},{"seq":"21","stop":"242","fare":"7.1","fareHoliday":"14.2"},{"seq":"22","stop":"243","fare":"7.1","fareHoliday":"14.2"},{"seq":"23","stop":"32","fare":"7.1","fareHoliday":"14.2"},{"seq":"24","stop":"30","fare":"7.1","fareHoliday":"14.2"},{"seq":"25","stop":"244","fare":"7.1","fareHoliday":"14.2"},{"seq":"26","stop":"245","fare":"7.1","fareHoliday":"14.2"},{"seq":"27","stop":"246","fare":"7.1","fareHoliday":"14.2"},{"seq":"28","stop":"247","fare":"7.1","fareHoliday":"14.2"},{"seq":"29","stop":"248","fare":"7.1","fareHoliday":"14.2"},{"seq":"30","stop":"249","fare":"7.1","fareHoliday":"14.2"},{"seq":"31","stop":"250","fare":"7.1","fareHoliday":"14.2"},{"seq":"32","stop":"251","fare":"7.1","fareHoliday":"14.2"},{"seq":"33","stop":"252","fare":"7.1","fareHoliday":"14.2"},{"seq":"34","stop":"253","fare":"7.1","fareHoliday":"14.2"},{"seq":"35","stop":"254","fare":"7.1","fareHoliday":"14.2"},{"seq":"36","stop":"255","fare":"7.1","fareHoliday":"14.2"},{"seq":"37","stop":"179","fare":"7.1","fareHoliday":"14.2"},{"seq":"38","stop":"64","fare":"7.1","fareHoliday":"14.2"},{"seq":"39","stop":"65","fare":"7.1","fareHoliday":"14.2"},{"seq":"40","stop":"66","fare":"7.1","fareHoliday":"14.2"},{"seq":"41","stop":"67","fare":"7.1","fareHoliday":"14.2"},{"seq":"42","stop":"68","fare":"2.8","fareHoliday":"5.6"},{"seq":"43","stop":"69","fare":"2.8","fareHoliday":"5.6"},{"seq":"44","stop":"70","fare":"2.8","fareHoliday":"5.6"},{"seq":"45","stop":"71","fare":"2.8","fareHoliday":"5.6"},{"seq":"46","stop":"72","fare":"2.8","fareHoliday":"5.6"},{"seq":"47","stop":"73","fare":"2.8","fareHoliday":"5.6"},{"seq":"48","stop":"74","fare":"2.8","fareHoliday":"5.6"},{"seq":"49","stop":"185","fare":"2.8","fareHoliday":"5.6"},{"seq":"50","stop":"76","fare":"2.8","fareHoliday":"5.6"},{"seq":"51","stop":"77","fare":"2.8","fareHoliday":"5.6"},{"seq":"52","stop":"78","fare":"2.8","fareHoliday":"5.6"},{"seq":"53","stop":"79","fare":"0.0","fareHoliday":"0.0"}]}},"11A":{"16":{"orig_en":"Shek Pik","dest_en":"Tung Chung Station Bus Terminus","orig_tc":"石壁","dest_tc":"東涌站巴士總站","service_type":"Normal","stops":[{"seq":"1","stop":"40","fare":"10.1","fareHoliday":"17.6"},{"seq":"2","stop":"235","fare":"10.1","fareHoliday":"17.6"},{"seq":"3","stop":"236","fare":"10.1","fareHoliday":"17.6"},{"seq":"4","stop":"237","fare":"7.1","fareHoliday":"14.3"},{"seq":"5","stop":"238","fare":"7.1","fareHoliday":"14.3"},{"seq":"6","stop":"239","fare":"7.1","fareHoliday":"14.3"},{"seq":"7","stop":"240","fare":"7.1","fareHoliday":"14.3"},{"seq":"8","stop":"241","fare":"7.1","fareHoliday":"14.3"},{"seq":"9","stop":"242","fare":"7.1","fareHoliday":"14.3"},{"seq":"10","stop":"243","fare":"7.1","fareHoliday":"14.3"},{"seq":"11","stop":"32","fare":"7.1","fareHoliday":"14.3"},{"seq":"12","stop":"30","fare":"7.1","fareHoliday":"14.3"},{"seq":"13","stop":"244","fare":"7.1","fareHoliday":"14.3"},{"seq":"14","stop":"245","fare":"7.1","fareHoliday":"14.3"},{"seq":"15","stop":"246","fare":"7.1","fareHoliday":"14.3"},{"seq":"16","stop":"247","fare":"7.1","fareHoliday":"14.3"},{"seq":"17","stop":"248","fare":"7.1","fareHoliday":"14.3"},{"seq":"18","stop":"249","fare":"7.1","fareHoliday":"14.3"},{"seq":"19","stop":"250","fare":"7.1","fareHoliday":"14.3"},{"seq":"20","stop":"251","fare":"7.1","fareHoliday":"14.3"},{"seq":"21","stop":"252","fare":"7.1","fareHoliday":"14.3"},{"seq":"22","stop":"253","fare":"7.1","fareHoliday":"14.3"},{"seq":"23","stop":"254","fare":"7.1","fareHoliday":"14.3"},{"seq":"24","stop":"255","fare":"7.1","fareHoliday":"14.3"},{"seq":"25","stop":"179","fare":"7.1","fareHoliday":"14.3"},{"seq":"26","stop":"64","fare":"7.1","fareHoliday":"14.3"},{"seq":"27","stop":"65","fare":"7.1","fareHoliday":"14.3"},{"seq":"28","stop":"66","fare":"7.1","fareHoliday":"14.3"},{"seq":"29","stop":"67","fare":"7.1","fareHoliday":"14.3"},{"seq":"30","stop":"68","fare":"2.8","fareHoliday":"5.6"},{"seq":"31","stop":"69","fare":"2.8","fareHoliday":"5.6"},{"seq":"32","stop":"70","fare":"2.8","fareHoliday":"5.6"},{"seq":"33","stop":"71","fare":"2.8","fareHoliday":"5.6"},{"seq":"34","stop":"72","fare":"2.8","fareHoliday":"5.6"},{"seq":"35","stop":"73","fare":"2.8","fareHoliday":"5.6"},{"seq":"36","stop":"74","fare":"2.8","fareHoliday":"5.6"},{"seq":"37","stop":"77","fare":"2.8","fareHoliday":"5.6"},{"seq":"38","stop":"78","fare":"2.8","fareHoliday":"5.6"},{"seq":"39","stop":"79","fare":"0.0","fareHoliday":"0.0"}]},"15":{"orig_en":"Tung Chung Station Bus Terminus","dest_en":"Shek Pik","orig_tc":"東涌站巴士總站","dest_tc":"石壁","service_type":"Normal","stops":[{"seq":"1","stop":"278","fare":"10.1","fareHoliday":"17.6"},{"seq":"2","stop":"80","fare":"10.1","fareHoliday":"17.6"},{"seq":"3","stop":"81","fare":"10.1","fareHoliday":"17.6"},{"seq":"4","stop":"94","fare":"10.1","fareHoliday":"17.6"},{"seq":"5","stop":"279","fare":"10.1","fareHoliday":"17.6"},{"seq":"6","stop":"280","fare":"10.1","fareHoliday":"17.6"},{"seq":"7","stop":"282","fare":"10.1","fareHoliday":"17.6"},{"seq":"8","stop":"283","fare":"10.1","fareHoliday":"17.6"},{"seq":"9","stop":"284","fare":"10.1","fareHoliday":"17.6"},{"seq":"10","stop":"286","fare":"10.1","fareHoliday":"17.6"},{"seq":"11","stop":"287","fare":"10.1","fareHoliday":"17.6"},{"seq":"12","stop":"288","fare":"10.1","fareHoliday":"17.6"},{"seq":"13","stop":"273","fare":"10.1","fareHoliday":"17.6"},{"seq":"14","stop":"83","fare":"10.1","fareHoliday":"17.6"},{"seq":"15","stop":"19","fare":"7.1","fareHoliday":"13.3"},{"seq":"16","stop":"20","fare":"7.1","fareHoliday":"13.3"},{"seq":"17","stop":"21","fare":"7.1","fareHoliday":"13.3"},{"seq":"18","stop":"22","fare":"7.1","fareHoliday":"13.3"},{"seq":"19","stop":"23","fare":"7.1","fareHoliday":"13.3"},{"seq":"20","stop":"24","fare":"7.1","fareHoliday":"13.3"},{"seq":"21","stop":"25","fare":"7.1","fareHoliday":"13.3"},{"seq":"22","stop":"26","fare":"7.1","fareHoliday":"13.3"},{"seq":"23","stop":"27","fare":"4.2","fareHoliday":"6.0"},{"seq":"24","stop":"28","fare":"4.2","fareHoliday":"6.0"},{"seq":"25","stop":"32","fare":"4.2","fareHoliday":"6.0"},{"seq":"26","stop":"30","fare":"4.2","fareHoliday":"6.0"},{"seq":"27","stop":"31","fare":"4.2","fareHoliday":"6.0"},{"seq":"28","stop":"178","fare":"4.2","fareHoliday":"6.0"},{"seq":"29","stop":"33","fare":"4.2","fareHoliday":"6.0"},{"seq":"30","stop":"34","fare":"4.2","fareHoliday":"6.0"},{"seq":"31","stop":"35","fare":"4.2","fareHoliday":"6.0"},{"seq":"32","stop":"36","fare":"4.2","fareHoliday":"6.0"},{"seq":"33","stop":"37","fare":"4.2","fareHoliday":"6.0"},{"seq":"34","stop":"38","fare":"4.2","fareHoliday":"6.0"},{"seq":"35","stop":"39","fare":"4.2","fareHoliday":"6.0"},{"seq":"36","stop":"41","fare":"4.2","fareHoliday":"6.0"},{"seq":"37","stop":"40","fare":"0.0","fareHoliday":"0.0"}]}},"21":{"19":{"orig_en":"Ngong Ping","dest_en":"Tai O","orig_tc":"昂坪","dest_tc":"大澳","service_type":"Normal","stops":[{"seq":"1","stop":"270","fare":"7.9","fareHoliday":"19.2"},{"seq":"2","stop":"271","fare":"7.9","fareHoliday":"19.2"},{"seq":"3","stop":"43","fare":"2.8","fareHoliday":"6.5"},{"seq":"4","stop":"44","fare":"2.8","fareHoliday":"6.5"},{"seq":"5","stop":"45","fare":"2.8","fareHoliday":"6.5"},{"seq":"6","stop":"46","fare":"2.8","fareHoliday":"6.5"},{"seq":"7","stop":"47","fare":"2.8","fareHoliday":"6.5"},{"seq":"8","stop":"48","fare":"2.8","fareHoliday":"6.5"},{"seq":"9","stop":"49","fare":"2.8","fareHoliday":"6.5"},{"seq":"10","stop":"84","fare":"2.8","fareHoliday":"6.5"},{"seq":"11","stop":"51","fare":"2.8","fareHoliday":"6.5"},{"seq":"12","stop":"52","fare":"2.8","fareHoliday":"6.5"},{"seq":"13","stop":"53","fare":"2.8","fareHoliday":"6.5"},{"seq":"14","stop":"54","fare":"2.8","fareHoliday":"6.5"},{"seq":"15","stop":"55","fare":"0.0","fareHoliday":"0.0"}]},"20":{"orig_en":"Tai O","dest_en":"Ngong Ping","orig_tc":"大澳","dest_tc":"昂坪","service_type":"Normal","stops":[{"seq":"1","stop":"221","fare":"7.9","fareHoliday":"19.2"},{"seq":"2","stop":"222","fare":"7.9","fareHoliday":"19.2"},{"seq":"3","stop":"224","fare":"7.9","fareHoliday":"19.2"},{"seq":"4","stop":"225","fare":"7.9","fareHoliday":"19.2"},{"seq":"5","stop":"226","fare":"7.9","fareHoliday":"19.2"},{"seq":"6","stop":"227","fare":"7.9","fareHoliday":"19.2"},{"seq":"7","stop":"228","fare":"7.9","fareHoliday":"19.2"},{"seq":"8","stop":"229","fare":"7.9","fareHoliday":"19.2"},{"seq":"9","stop":"230","fare":"7.9","fareHoliday":"19.2"},{"seq":"10","stop":"232","fare":"7.9","fareHoliday":"19.2"},{"seq":"11","stop":"233","fare":"5.6","fareHoliday":"12.6"},{"seq":"12","stop":"59","fare":"5.6","fareHoliday":"12.6"},{"seq":"13","stop":"60","fare":"5.6","fareHoliday":"12.6"},{"seq":"14","stop":"62","fare":"0.0","fareHoliday":"0.0"}]}},"23":{"22":{"orig_en":"Ngong Ping","dest_en":"Tung Chung Tat Tung Road Bus Terminus","orig_tc":"昂坪","dest_tc":"東涌達東路巴士總站","service_type":"Normal","stops":[{"seq":"1","stop":"270","fare":"20.4","fareHoliday":"37.0"},{"seq":"2","stop":"271","fare":"20.4","fareHoliday":"37.0"},{"seq":"3","stop":"43","fare":"13.3","fareHoliday":"25.3"},{"seq":"4","stop":"234","fare":"10.9","fareHoliday":"20.5"},{"seq":"5","stop":"235","fare":"10.9","fareHoliday":"20.5"},{"seq":"6","stop":"236","fare":"10.9","fareHoliday":"20.5"},{"seq":"7","stop":"237","fare":"7.3","fareHoliday":"17.0"},{"seq":"8","stop":"238","fare":"7.3","fareHoliday":"17.0"},{"seq":"9","stop":"239","fare":"7.3","fareHoliday":"17.0"},{"seq":"10","stop":"240","fare":"7.3","fareHoliday":"17.0"},{"seq":"11","stop":"241","fare":"7.3","fareHoliday":"17.0"},{"seq":"12","stop":"242","fare":"7.3","fareHoliday":"17.0"},{"seq":"13","stop":"243","fare":"7.3","fareHoliday":"17.0"},{"seq":"14","stop":"244","fare":"7.3","fareHoliday":"17.0"},{"seq":"15","stop":"245","fare":"7.3","fareHoliday":"17.0"},{"seq":"16","stop":"246","fare":"7.3","fareHoliday":"17.0"},{"seq":"17","stop":"247","fare":"7.3","fareHoliday":"17.0"},{"seq":"18","stop":"248","fare":"7.3","fareHoliday":"17.0"},{"seq":"19","stop":"249","fare":"7.3","fareHoliday":"17.0"},{"seq":"20","stop":"250","fare":"7.3","fareHoliday":"17.0"},{"seq":"21","stop":"251","fare":"7.3","fareHoliday":"17.0"},{"seq":"22","stop":"252","fare":"7.3","fareHoliday":"17.0"},{"seq":"23","stop":"253","fare":"7.3","fareHoliday":"17.0"},{"seq":"24","stop":"254","fare":"7.3","fareHoliday":"17.0"},{"seq":"25","stop":"255","fare":"7.3","fareHoliday":"17.0"},{"seq":"26","stop":"179","fare":"7.3","fareHoliday":"17.0"},{"seq":"27","stop":"64","fare":"7.3","fareHoliday":"17.0"},{"seq":"28","stop":"65","fare":"7.3","fareHoliday":"17.0"},{"seq":"29","stop":"66","fare":"7.3","fareHoliday":"17.0"},{"seq":"30","stop":"67","fare":"7.3","fareHoliday":"17.0"},{"seq":"31","stop":"68","fare":"2.8","fareHoliday":"6.5"},{"seq":"32","stop":"69","fare":"2.8","fareHoliday":"6.5"},{"seq":"33","stop":"70","fare":"2.8","fareHoliday":"6.5"},{"seq":"34","stop":"71","fare":"2.8","fareHoliday":"6.5"},{"seq":"35","stop":"72","fare":"2.8","fareHoliday":"6.5"},{"seq":"36","stop":"73","fare":"2.8","fareHoliday":"6.5"},{"seq":"37","stop":"74","fare":"2.8","fareHoliday":"6.5"},{"seq":"38","stop":"77","fare":"2.8","fareHoliday":"6.5"},{"seq":"39","stop":"78","fare":"2.8","fareHoliday":"6.5"},{"seq":"40","stop":"318","fare":"0.0","fareHoliday":"0.0"}]},"21":{"orig_en":"Tung Chung Tat Tung Road Bus Terminus","dest_en":"Ngong Ping","orig_tc":"東涌達東路巴士總站","dest_tc":"昂坪","service_type":"Normal","stops":[{"seq":"1","stop":"317","fare":"20.4","fareHoliday":"37.0"},{"seq":"2","stop":"81","fare":"20.4","fareHoliday":"37.0"},{"seq":"3","stop":"94","fare":"20.4","fareHoliday":"37.0"},{"seq":"4","stop":"279","fare":"20.4","fareHoliday":"37.0"},{"seq":"5","stop":"280","fare":"20.4","fareHoliday":"37.0"},{"seq":"6","stop":"282","fare":"20.4","fareHoliday":"37.0"},{"seq":"7","stop":"283","fare":"20.4","fareHoliday":"37.0"},{"seq":"8","stop":"284","fare":"20.4","fareHoliday":"37.0"},{"seq":"9","stop":"286","fare":"20.4","fareHoliday":"37.0"},{"seq":"10","stop":"287","fare":"20.4","fareHoliday":"37.0"},{"seq":"11","stop":"288","fare":"20.4","fareHoliday":"37.0"},{"seq":"12","stop":"273","fare":"20.4","fareHoliday":"37.0"},{"seq":"13","stop":"83","fare":"20.4","fareHoliday":"37.0"},{"seq":"14","stop":"19","fare":"13.3","fareHoliday":"25.3"},{"seq":"15","stop":"20","fare":"13.3","fareHoliday":"25.3"},{"seq":"16","stop":"21","fare":"13.3","fareHoliday":"25.3"},{"seq":"17","stop":"22","fare":"13.3","fareHoliday":"25.3"},{"seq":"18","stop":"23","fare":"13.3","fareHoliday":"25.3"},{"seq":"19","stop":"24","fare":"13.3","fareHoliday":"25.3"},{"seq":"20","stop":"25","fare":"13.3","fareHoliday":"25.3"},{"seq":"21","stop":"26","fare":"13.3","fareHoliday":"25.3"},{"seq":"22","stop":"27","fare":"13.3","fareHoliday":"25.3"},{"seq":"23","stop":"28","fare":"13.3","fareHoliday":"25.3"},{"seq":"24","stop":"31","fare":"13.3","fareHoliday":"25.3"},{"seq":"25","stop":"178","fare":"13.3","fareHoliday":"25.3"},{"seq":"26","stop":"33","fare":"13.3","fareHoliday":"25.3"},{"seq":"27","stop":"34","fare":"13.3","fareHoliday":"25.3"},{"seq":"28","stop":"35","fare":"13.3","fareHoliday":"25.3"},{"seq":"29","stop":"36","fare":"13.3","fareHoliday":"25.3"},{"seq":"30","stop":"37","fare":"13.3","fareHoliday":"25.3"},{"seq":"31","stop":"38","fare":"13.3","fareHoliday":"25.3"},{"seq":"32","stop":"39","fare":"8.0","fareHoliday":"19.2"},{"seq":"33","stop":"41","fare":"8.0","fareHoliday":"19.2"},{"seq":"34","stop":"42","fare":"8.0","fareHoliday":"19.2"},{"seq":"35","stop":"269","fare":"5.6","fareHoliday":"12.6"},{"seq":"36","stop":"59","fare":"5.6","fareHoliday":"12.6"},{"seq":"37","stop":"60","fare":"5.6","fareHoliday":"12.6"},{"seq":"38","stop":"62","fare":"0.0","fareHoliday":"0.0"}]}},"34":{"24":{"orig_en":"Shek Mun Kap","dest_en":"Tung Chung Tat Tung Road Bus Terminus","orig_tc":"石門甲","dest_tc":"東涌達東路巴士總站","service_type":"Normal","stops":[{"seq":"1","stop":"93","fare":"5.1","fareHoliday":"5.1"},{"seq":"2","stop":"292","fare":"5.1","fareHoliday":"5.1"},{"seq":"3","stop":"68","fare":"5.1","fareHoliday":"5.1"},{"seq":"4","stop":"69","fare":"5.1","fareHoliday":"5.1"},{"seq":"5","stop":"70","fare":"5.1","fareHoliday":"5.1"},{"seq":"6","stop":"71","fare":"5.1","fareHoliday":"5.1"},{"seq":"7","stop":"72","fare":"5.1","fareHoliday":"5.1"},{"seq":"8","stop":"73","fare":"5.1","fareHoliday":"5.1"},{"seq":"9","stop":"91","fare":"5.1","fareHoliday":"5.1"},{"seq":"10","stop":"74","fare":"5.1","fareHoliday":"5.1"},{"seq":"11","stop":"185","fare":"5.1","fareHoliday":"5.1"},{"seq":"12","stop":"289","fare":"3.7","fareHoliday":"3.7"},{"seq":"13","stop":"76","fare":"3.7","fareHoliday":"3.7"},{"seq":"14","stop":"77","fare":"3.7","fareHoliday":"3.7"},{"seq":"15","stop":"78","fare":"3.7","fareHoliday":"3.7"},{"seq":"16","stop":"318","fare":"0.0","fareHoliday":"0.0"}]},"23":{"orig_en":"Tung Chung Tat Tung Road Bus Terminus","dest_en":"Shek Mun Kap","orig_tc":"東涌達東路巴士總站","dest_tc":"石門甲","service_type":"Normal","stops":[{"seq":"1","stop":"317","fare":"5.1","fareHoliday":"5.1"},{"seq":"2","stop":"80","fare":"5.1","fareHoliday":"5.1"},{"seq":"3","stop":"81","fare":"5.1","fareHoliday":"5.1"},{"seq":"4","stop":"185","fare":"5.1","fareHoliday":"5.1"},{"seq":"5","stop":"289","fare":"3.7","fareHoliday":"3.7"},{"seq":"6","stop":"76","fare":"3.7","fareHoliday":"3.7"},{"seq":"7","stop":"90","fare":"3.7","fareHoliday":"3.7"},{"seq":"8","stop":"91","fare":"3.7","fareHoliday":"3.7"},{"seq":"9","stop":"94","fare":"3.7","fareHoliday":"3.7"},{"seq":"10","stop":"279","fare":"3.7","fareHoliday":"3.7"},{"seq":"11","stop":"280","fare":"3.7","fareHoliday":"3.7"},{"seq":"12","stop":"282","fare":"3.7","fareHoliday":"3.7"},{"seq":"13","stop":"283","fare":"3.7","fareHoliday":"3.7"},{"seq":"14","stop":"92","fare":"3.7","fareHoliday":"3.7"},{"seq":"15","stop":"291","fare":"0.0","fareHoliday":"0.0"}]}},"34S":{"71":{"orig_en":"Tung Chung Tat Tung Road Bus Terminus","dest_en":"Cemetery Area No. 18 (Circular)","orig_tc":"東涌達東路巴士總站","dest_tc":"十八區墳場 (循環線)","service_type":"Special","stops":[{"seq":"1","stop":"317","fare":"0.0","fareHoliday":"5.1"},{"seq":"2","stop":"80","fare":"0.0","fareHoliday":"5.1"},{"seq":"3","stop":"81","fare":"0.0","fareHoliday":"5.1"},{"seq":"4","stop":"185","fare":"0.0","fareHoliday":"5.1"},{"seq":"5","stop":"89","fare":"0.0","fareHoliday":"5.1"},{"seq":"6","stop":"76","fare":"0.0","fareHoliday":"5.1"},{"seq":"7","stop":"90","fare":"0.0","fareHoliday":"5.1"},{"seq":"8","stop":"73","fare":"0.0","fareHoliday":"5.1"},{"seq":"9","stop":"279","fare":"0.0","fareHoliday":"5.1"},{"seq":"10","stop":"71","fare":"0.0","fareHoliday":"5.1"},{"seq":"11","stop":"70","fare":"0.0","fareHoliday":"5.1"},{"seq":"12","stop":"283","fare":"0.0","fareHoliday":"5.1"},{"seq":"13","stop":"284","fare":"0.0","fareHoliday":"5.1"},{"seq":"14","stop":"286","fare":"0.0","fareHoliday":"5.1"},{"seq":"15","stop":"68","fare":"0.0","fareHoliday":"5.1"},{"seq":"16","stop":"283","fare":"0.0","fareHoliday":"5.1"},{"seq":"17","stop":"70","fare":"0.0","fareHoliday":"5.1"},{"seq":"18","stop":"71","fare":"0.0","fareHoliday":"5.1"},{"seq":"19","stop":"72","fare":"0.0","fareHoliday":"5.1"},{"seq":"20","stop":"94","fare":"0.0","fareHoliday":"5.1"},{"seq":"21","stop":"74","fare":"0.0","fareHoliday":"5.1"},{"seq":"22","stop":"185","fare":"0.0","fareHoliday":"5.1"},{"seq":"23","stop":"89","fare":"0.0","fareHoliday":"5.1"},{"seq":"24","stop":"76","fare":"0.0","fareHoliday":"5.1"},{"seq":"25","stop":"77","fare":"0.0","fareHoliday":"5.1"},{"seq":"26","stop":"78","fare":"0.0","fareHoliday":"5.1"},{"seq":"27","stop":"317","fare":"0.0","fareHoliday":"0.0"}]}},"36":{"101":{"orig_en":"Tung Chung Tat Tung Road Bus Terminus","dest_en":"Disneyland","orig_tc":"東涌達東路巴士總站","dest_tc":"迪士尼樂園","service_type":"Normal","stops":[{"seq":"1","stop":"317","fare":"10.7","fareHoliday":"10.7"},{"seq":"2","stop":"100","fare":"10.7","fareHoliday":"10.7"},{"seq":"3","stop":"295","fare":"10.7","fareHoliday":"10.7"},{"seq":"4","stop":"98","fare":"10.7","fareHoliday":"10.7"},{"seq":"5","stop":"95","fare":"10.7","fareHoliday":"10.7"},{"seq":"6","stop":"327","fare":"0.0","fareHoliday":"0.0"}]},"102":{"orig_en":"Disneyland","dest_en":"Tung Chung Tat Tung Road Bus Terminus","orig_tc":"迪士尼樂園","dest_tc":"東涌達東路巴士總站","service_type":"Normal","stops":[{"seq":"1","stop":"328","fare":"10.7","fareHoliday":"10.7"},{"seq":"2","stop":"293","fare":"5.1","fareHoliday":"5.1"},{"seq":"3","stop":"96","fare":"5.1","fareHoliday":"5.1"},{"seq":"4","stop":"97","fare":"5.1","fareHoliday":"5.1"},{"seq":"5","stop":"294","fare":"5.1","fareHoliday":"5.1"},{"seq":"6","stop":"99","fare":"5.1","fareHoliday":"5.1"},{"seq":"7","stop":"80","fare":"5.1","fareHoliday":"5.1"},{"seq":"8","stop":"78","fare":"5.1","fareHoliday":"5.1"},{"seq":"9","stop":"318","fare":"0.0","fareHoliday":"0.0"}]}},"36M":{"115":{"orig_en":"Cheung Yuet House Cheung Tung Estate","dest_en":"Sunny Bay Station","orig_tc":"翔東邨(翔月樓)","dest_tc":"欣澳站","service_type":"Special","stops":[{"seq":"1","stop":"343","fare":"10.7","fareHoliday":"0.0"},{"seq":"2","stop":"342","fare":"10.7","fareHoliday":"0.0"},{"seq":"3","stop":"329","fare":"10.7","fareHoliday":"0.0"},{"seq":"4","stop":"330","fare":"10.7","fareHoliday":"0.0"},{"seq":"5","stop":"339","fare":"0.0","fareHoliday":"0.0"}]}},"36X":{"100":{"orig_en":"Mun Tung Estate","dest_en":"Disneyland","orig_tc":"滿東邨","dest_tc":"迪士尼樂園","service_type":"Normal","stops":[{"seq":"1","stop":"309","fare":"10.7","fareHoliday":"0.0"},{"seq":"2","stop":"306","fare":"10.7","fareHoliday":"0.0"},{"seq":"3","stop":"77","fare":"10.7","fareHoliday":"0.0"},{"seq":"4","stop":"327","fare":"0.0","fareHoliday":"0.0"}]}},"37":{"80":{"orig_en":"Ying Tung Estate","dest_en":"Yat Tung Estate","orig_tc":"迎東邨","dest_tc":"逸東邨","service_type":"Normal","stops":[{"seq":"1","stop":"297","fare":"3.9","fareHoliday":"0.0"},{"seq":"2","stop":"191","fare":"3.9","fareHoliday":"0.0"},{"seq":"3","stop":"110","fare":"3.9","fareHoliday":"0.0"},{"seq":"4","stop":"298","fare":"3.9","fareHoliday":"0.0"},{"seq":"5","stop":"111","fare":"3.9","fareHoliday":"0.0"},{"seq":"6","stop":"112","fare":"3.9","fareHoliday":"0.0"},{"seq":"7","stop":"299","fare":"3.9","fareHoliday":"0.0"},{"seq":"8","stop":"310","fare":"3.9","fareHoliday":"0.0"},{"seq":"9","stop":"101","fare":"3.9","fareHoliday":"0.0"},{"seq":"10","stop":"102","fare":"3.9","fareHoliday":"0.0"},{"seq":"11","stop":"103","fare":"3.9","fareHoliday":"0.0"},{"seq":"12","stop":"104","fare":"3.9","fareHoliday":"0.0"},{"seq":"13","stop":"185","fare":"3.9","fareHoliday":"0.0"},{"seq":"14","stop":"88","fare":"3.9","fareHoliday":"0.0"},{"seq":"15","stop":"89","fare":"0.0","fareHoliday":"0.0"}]},"78":{"orig_en":"Yat Tung Estate","dest_en":"Ying Tung Estate","orig_tc":"逸東邨","dest_tc":"迎東邨","service_type":"Normal","stops":[{"seq":"1","stop":"289","fare":"3.9","fareHoliday":"0.0"},{"seq":"2","stop":"76","fare":"3.9","fareHoliday":"0.0"},{"seq":"3","stop":"309","fare":"3.9","fareHoliday":"0.0"},{"seq":"4","stop":"101","fare":"3.9","fareHoliday":"0.0"},{"seq":"5","stop":"102","fare":"3.9","fareHoliday":"0.0"},{"seq":"6","stop":"103","fare":"3.9","fareHoliday":"0.0"},{"seq":"7","stop":"104","fare":"3.9","fareHoliday":"0.0"},{"seq":"8","stop":"77","fare":"3.9","fareHoliday":"0.0"},{"seq":"9","stop":"78","fare":"3.9","fareHoliday":"0.0"},{"seq":"10","stop":"79","fare":"3.9","fareHoliday":"0.0"},{"seq":"11","stop":"107","fare":"3.9","fareHoliday":"0.0"},{"seq":"12","stop":"108","fare":"3.9","fareHoliday":"0.0"},{"seq":"13","stop":"186","fare":"3.9","fareHoliday":"0.0"},{"seq":"14","stop":"109","fare":"3.9","fareHoliday":"0.0"},{"seq":"15","stop":"110","fare":"3.9","fareHoliday":"0.0"},{"seq":"16","stop":"190","fare":"3.9","fareHoliday":"0.0"},{"seq":"17","stop":"193","fare":"0.0","fareHoliday":"0.0"}]}},"37A":{"116":{"orig_en":"Cheung Yuet House Cheung Tung Estate","dest_en":"Tung Chung Station Bus Terminus (Circular)","orig_tc":"翔東邨(翔月樓)","dest_tc":"東涌站巴士總站 (循環線)","service_type":"Normal","stops":[{"seq":"1","stop":"343","fare":"3.9","fareHoliday":"3.9"},{"seq":"2","stop":"342","fare":"3.9","fareHoliday":"3.9"},{"seq":"3","stop":"329","fare":"3.9","fareHoliday":"3.9"},{"seq":"4","stop":"330","fare":"3.9","fareHoliday":"3.9"},{"seq":"5","stop":"77","fare":"3.9","fareHoliday":"3.9"},{"seq":"6","stop":"321","fare":"3.9","fareHoliday":"3.9"},{"seq":"7","stop":"278","fare":"3.9","fareHoliday":"3.9"},{"seq":"8","stop":"81","fare":"3.9","fareHoliday":"3.9"},{"seq":"9","stop":"331","fare":"3.9","fareHoliday":"3.9"},{"seq":"10","stop":"341","fare":"3.9","fareHoliday":"3.9"},{"seq":"11","stop":"344","fare":"0.0","fareHoliday":"0.0"}]}},"37H":{"96":{"orig_en":"Ying Tung Estate","dest_en":"North Lantau Hospital (Circular)","orig_tc":"迎東邨","dest_tc":"北大嶼山醫院 (循環線)","service_type":"Normal","stops":[{"seq":"1","stop":"297","fare":"3.9","fareHoliday":"3.9"},{"seq":"2","stop":"191","fare":"3.9","fareHoliday":"3.9"},{"seq":"3","stop":"298","fare":"3.9","fareHoliday":"3.9"},{"seq":"4","stop":"111","fare":"3.9","fareHoliday":"3.9"},{"seq":"5","stop":"112","fare":"3.9","fareHoliday":"3.9"},{"seq":"6","stop":"299","fare":"3.9","fareHoliday":"3.9"},{"seq":"7","stop":"106","fare":"3.9","fareHoliday":"3.9"},{"seq":"8","stop":"78","fare":"3.9","fareHoliday":"3.9"},{"seq":"9","stop":"278","fare":"3.9","fareHoliday":"3.9"},{"seq":"10","stop":"81","fare":"3.9","fareHoliday":"3.9"},{"seq":"11","stop":"185","fare":"3.9","fareHoliday":"3.9"},{"seq":"12","stop":"188","fare":"3.9","fareHoliday":"3.9"},{"seq":"13","stop":"338","fare":"3.9","fareHoliday":"3.9"},{"seq":"14","stop":"74","fare":"3.9","fareHoliday":"3.9"},{"seq":"15","stop":"310","fare":"3.9","fareHoliday":"3.9"},{"seq":"16","stop":"103","fare":"3.9","fareHoliday":"3.9"},{"seq":"17","stop":"104","fare":"3.9","fareHoliday":"3.9"},{"seq":"18","stop":"320","fare":"3.9","fareHoliday":"3.9"},{"seq":"19","stop":"89","fare":"3.9","fareHoliday":"3.9"},{"seq":"20","stop":"322","fare":"3.9","fareHoliday":"3.9"},{"seq":"21","stop":"77","fare":"3.9","fareHoliday":"3.9"},{"seq":"22","stop":"321","fare":"3.9","fareHoliday":"3.9"},{"seq":"23","stop":"332","fare":"3.9","fareHoliday":"3.9"},{"seq":"24","stop":"319","fare":"3.9","fareHoliday":"3.9"},{"seq":"25","stop":"107","fare":"3.9","fareHoliday":"3.9"},{"seq":"26","stop":"108","fare":"3.9","fareHoliday":"3.9"},{"seq":"27","stop":"186","fare":"3.9","fareHoliday":"3.9"},{"seq":"28","stop":"109","fare":"3.9","fareHoliday":"3.9"},{"seq":"29","stop":"194","fare":"3.9","fareHoliday":"3.9"},{"seq":"30","stop":"190","fare":"3.9","fareHoliday":"3.9"},{"seq":"31","stop":"193","fare":"0.0","fareHoliday":"0.0"}]}},"37M":{"82":{"orig_en":"Ying Tung Estate","dest_en":"Tung Chung Station Bus Terminus (Circular)","orig_tc":"迎東邨","dest_tc":"東涌站巴士總站 (循環線)","service_type":"Normal","stops":[{"seq":"1","stop":"297","fare":"3.9","fareHoliday":"3.9"},{"seq":"2","stop":"191","fare":"3.9","fareHoliday":"3.9"},{"seq":"3","stop":"192","fare":"3.9","fareHoliday":"3.9"},{"seq":"4","stop":"329","fare":"3.9","fareHoliday":"3.9"},{"seq":"5","stop":"330","fare":"3.9","fareHoliday":"3.9"},{"seq":"6","stop":"78","fare":"3.9","fareHoliday":"3.9"},{"seq":"7","stop":"79","fare":"3.9","fareHoliday":"3.9"},{"seq":"8","stop":"340","fare":"3.9","fareHoliday":"3.9"},{"seq":"9","stop":"324","fare":"3.9","fareHoliday":"3.9"},{"seq":"10","stop":"303","fare":"3.9","fareHoliday":"3.9"},{"seq":"11","stop":"190","fare":"3.9","fareHoliday":"3.9"},{"seq":"12","stop":"193","fare":"0.0","fareHoliday":"0.0"}]}},"37P":{"63":{"orig_en":"Yung Yat House (Yu Tung Road)","dest_en":"Caribbean Coast","orig_tc":"逸東邨 (裕東路)","dest_tc":"映灣園","service_type":"Normal","stops":[{"seq":"1","stop":"104","fare":"3.9","fareHoliday":"0.0"},{"seq":"2","stop":"112","fare":"3.9","fareHoliday":"0.0"},{"seq":"3","stop":"315","fare":"0.0","fareHoliday":"0.0"}]}},"37S":{"75":{"orig_en":"Tung Chung Development Ferry Pier","dest_en":"Tung Chung Station Bus Terminus","orig_tc":"東涌發展碼頭","dest_tc":"東涌站巴士總站","service_type":"Normal","stops":[{"seq":"1","stop":"106","fare":"3.9","fareHoliday":"3.9"},{"seq":"2","stop":"78","fare":"3.9","fareHoliday":"3.9"},{"seq":"3","stop":"105","fare":"0.0","fareHoliday":"0.0"}]}},"38":{"30":{"orig_en":"Yat Tung Estate","dest_en":"Tung Chung Station Bus Terminus (Circular)","orig_tc":"逸東邨","dest_tc":"東涌站巴士總站 (循環線)","service_type":"Normal","stops":[{"seq":"1","stop":"289","fare":"3.8","fareHoliday":"3.8"},{"seq":"2","stop":"76","fare":"3.8","fareHoliday":"3.8"},{"seq":"3","stop":"77","fare":"3.8","fareHoliday":"3.8"},{"seq":"4","stop":"78","fare":"3.8","fareHoliday":"3.8"},{"seq":"5","stop":"105","fare":"3.8","fareHoliday":"3.8"},{"seq":"6","stop":"81","fare":"3.8","fareHoliday":"3.8"},{"seq":"7","stop":"185","fare":"3.8","fareHoliday":"3.8"},{"seq":"8","stop":"88","fare":"3.8","fareHoliday":"3.8"},{"seq":"9","stop":"89","fare":"0.0","fareHoliday":"0.0"}]}},"38X":{"29":{"orig_en":"Yat Tung Estate (Yu Tung Road)","dest_en":"Tung Chung Station Bus Terminus (Circular)","orig_tc":"逸東邨 (裕東路)","dest_tc":"東涌站巴士總站 (循環線)","service_type":"Normal","stops":[{"seq":"1","stop":"104","fare":"3.8","fareHoliday":"0.0"},{"seq":"2","stop":"185","fare":"3.8","fareHoliday":"0.0"},{"seq":"3","stop":"76","fare":"3.8","fareHoliday":"0.0"},{"seq":"4","stop":"77","fare":"3.8","fareHoliday":"0.0"},{"seq":"5","stop":"78","fare":"3.8","fareHoliday":"0.0"},{"seq":"6","stop":"105","fare":"3.8","fareHoliday":"0.0"},{"seq":"7","stop":"80","fare":"3.8","fareHoliday":"0.0"},{"seq":"8","stop":"81","fare":"3.8","fareHoliday":"0.0"},{"seq":"9","stop":"101","fare":"3.8","fareHoliday":"0.0"},{"seq":"10","stop":"102","fare":"3.8","fareHoliday":"0.0"},{"seq":"11","stop":"103","fare":"3.8","fareHoliday":"0.0"},{"seq":"12","stop":"306","fare":"0.0","fareHoliday":"0.0"}]}},"39M":{"95":{"orig_en":"Tung Chung Station Bus Terminus","dest_en":"Mun Tung Estate  (Circular Route)","orig_tc":"東涌站巴士總站","dest_tc":"滿東邨 (循環線)","service_type":"Normal","stops":[{"seq":"1","stop":"278","fare":"3.9","fareHoliday":"3.9"},{"seq":"2","stop":"81","fare":"3.9","fareHoliday":"3.9"},{"seq":"3","stop":"309","fare":"3.9","fareHoliday":"3.9"},{"seq":"4","stop":"103","fare":"3.9","fareHoliday":"3.9"},{"seq":"5","stop":"306","fare":"3.9","fareHoliday":"3.9"},{"seq":"6","stop":"77","fare":"3.9","fareHoliday":"3.9"},{"seq":"7","stop":"78","fare":"3.9","fareHoliday":"3.9"},{"seq":"8","stop":"79","fare":"0.0","fareHoliday":"0.0"}]}},"A35":{"90":{"orig_en":"Mui Wo Ferry Pier","dest_en":"HZMB Hong Kong Port","orig_tc":"梅窩碼頭","dest_tc":"大橋香港口岸","service_type":"Normal","stops":[{"seq":"1","stop":"1","fare":"20.0","fareHoliday":"32.4"},{"seq":"2","stop":"2","fare":"20.0","fareHoliday":"32.4"},{"seq":"3","stop":"3","fare":"20.0","fareHoliday":"32.4"},{"seq":"4","stop":"4","fare":"20.0","fareHoliday":"32.4"},{"seq":"5","stop":"5","fare":"20.0","fareHoliday":"32.4"},{"seq":"6","stop":"6","fare":"20.0","fareHoliday":"32.4"},{"seq":"7","stop":"7","fare":"20.0","fareHoliday":"32.4"},{"seq":"8","stop":"8","fare":"20.0","fareHoliday":"32.4"},{"seq":"9","stop":"9","fare":"20.0","fareHoliday":"32.4"},{"seq":"10","stop":"10","fare":"20.0","fareHoliday":"32.4"},{"seq":"11","stop":"11","fare":"17.5","fareHoliday":"26.9"},{"seq":"12","stop":"12","fare":"17.5","fareHoliday":"26.9"},{"seq":"13","stop":"13","fare":"17.5","fareHoliday":"26.9"},{"seq":"14","stop":"14","fare":"17.5","fareHoliday":"26.9"},{"seq":"15","stop":"15","fare":"17.5","fareHoliday":"26.9"},{"seq":"16","stop":"16","fare":"17.5","fareHoliday":"26.9"},{"seq":"17","stop":"17","fare":"17.5","fareHoliday":"26.9"},{"seq":"18","stop":"18","fare":"17.5","fareHoliday":"26.9"},{"seq":"19","stop":"83","fare":"17.5","fareHoliday":"26.9"},{"seq":"20","stop":"19","fare":"17.5","fareHoliday":"26.9"},{"seq":"21","stop":"20","fare":"17.5","fareHoliday":"26.9"},{"seq":"22","stop":"21","fare":"17.5","fareHoliday":"26.9"},{"seq":"23","stop":"22","fare":"17.5","fareHoliday":"26.9"},{"seq":"24","stop":"23","fare":"17.5","fareHoliday":"26.9"},{"seq":"25","stop":"24","fare":"17.5","fareHoliday":"26.9"},{"seq":"26","stop":"25","fare":"17.5","fareHoliday":"26.9"},{"seq":"27","stop":"26","fare":"17.5","fareHoliday":"26.9"},{"seq":"28","stop":"27","fare":"17.5","fareHoliday":"26.9"},{"seq":"29","stop":"28","fare":"13.6","fareHoliday":"21.9"},{"seq":"30","stop":"246","fare":"13.6","fareHoliday":"21.9"},{"seq":"31","stop":"247","fare":"13.6","fareHoliday":"21.9"},{"seq":"32","stop":"248","fare":"13.6","fareHoliday":"21.9"},{"seq":"33","stop":"249","fare":"13.6","fareHoliday":"21.9"},{"seq":"34","stop":"250","fare":"13.6","fareHoliday":"21.9"},{"seq":"35","stop":"251","fare":"13.6","fareHoliday":"21.9"},{"seq":"36","stop":"252","fare":"13.6","fareHoliday":"21.9"},{"seq":"37","stop":"253","fare":"13.6","fareHoliday":"21.9"},{"seq":"38","stop":"254","fare":"13.6","fareHoliday":"21.9"},{"seq":"39","stop":"255","fare":"13.6","fareHoliday":"21.9"},{"seq":"40","stop":"179","fare":"13.6","fareHoliday":"21.9"},{"seq":"41","stop":"64","fare":"13.6","fareHoliday":"21.9"},{"seq":"42","stop":"65","fare":"13.6","fareHoliday":"21.9"},{"seq":"43","stop":"66","fare":"13.6","fareHoliday":"21.9"},{"seq":"44","stop":"67","fare":"13.6","fareHoliday":"21.9"},{"seq":"45","stop":"68","fare":"9.7","fareHoliday":"14.2"},{"seq":"46","stop":"69","fare":"9.7","fareHoliday":"14.2"},{"seq":"47","stop":"70","fare":"9.7","fareHoliday":"14.2"},{"seq":"48","stop":"71","fare":"9.7","fareHoliday":"14.2"},{"seq":"49","stop":"72","fare":"9.7","fareHoliday":"14.2"},{"seq":"50","stop":"73","fare":"9.7","fareHoliday":"14.2"},{"seq":"51","stop":"74","fare":"9.7","fareHoliday":"14.2"},{"seq":"52","stop":"77","fare":"6.5","fareHoliday":"10.2"},{"seq":"53","stop":"78","fare":"6.5","fareHoliday":"10.2"},{"seq":"54","stop":"79","fare":"6.5","fareHoliday":"10.2"},{"seq":"55","stop":"114","fare":"6.5","fareHoliday":"10.2"},{"seq":"56","stop":"115","fare":"6.5","fareHoliday":"10.2"},{"seq":"57","stop":"116","fare":"6.5","fareHoliday":"10.2"},{"seq":"58","stop":"117","fare":"6.5","fareHoliday":"10.2"},{"seq":"59","stop":"335","fare":"6.5","fareHoliday":"10.2"},{"seq":"60","stop":"308","fare":"6.5","fareHoliday":"10.2"},{"seq":"61","stop":"313","fare":"0.0","fareHoliday":"0.0"}]},"91":{"orig_en":"HZMB Hong Kong Port","dest_en":"Mui Wo Ferry Pier","orig_tc":"大橋香港口岸","dest_tc":"梅窩碼頭","service_type":"Normal","stops":[{"seq":"1","stop":"307","fare":"20.0","fareHoliday":"32.4"},{"seq":"2","stop":"117","fare":"17.8","fareHoliday":"30.0"},{"seq":"3","stop":"118","fare":"17.8","fareHoliday":"30.0"},{"seq":"4","stop":"120","fare":"17.8","fareHoliday":"30.0"},{"seq":"5","stop":"335","fare":"17.8","fareHoliday":"30.0"},{"seq":"6","stop":"274","fare":"17.8","fareHoliday":"30.0"},{"seq":"7","stop":"277","fare":"17.8","fareHoliday":"30.0"},{"seq":"8","stop":"78","fare":"13.4","fareHoliday":"22.1"},{"seq":"9","stop":"79","fare":"13.4","fareHoliday":"22.1"},{"seq":"10","stop":"80","fare":"13.4","fareHoliday":"22.1"},{"seq":"11","stop":"81","fare":"13.4","fareHoliday":"22.1"},{"seq":"12","stop":"90","fare":"13.4","fareHoliday":"22.1"},{"seq":"13","stop":"94","fare":"13.4","fareHoliday":"22.1"},{"seq":"14","stop":"279","fare":"13.4","fareHoliday":"22.1"},{"seq":"15","stop":"280","fare":"13.4","fareHoliday":"22.1"},{"seq":"16","stop":"282","fare":"13.4","fareHoliday":"22.1"},{"seq":"17","stop":"283","fare":"13.4","fareHoliday":"22.1"},{"seq":"18","stop":"284","fare":"13.4","fareHoliday":"22.1"},{"seq":"19","stop":"286","fare":"13.4","fareHoliday":"22.1"},{"seq":"20","stop":"287","fare":"13.4","fareHoliday":"22.1"},{"seq":"21","stop":"288","fare":"13.4","fareHoliday":"22.1"},{"seq":"22","stop":"273","fare":"13.4","fareHoliday":"22.1"},{"seq":"23","stop":"83","fare":"13.4","fareHoliday":"22.1"},{"seq":"24","stop":"19","fare":"13.4","fareHoliday":"22.1"},{"seq":"25","stop":"20","fare":"13.4","fareHoliday":"22.1"},{"seq":"26","stop":"21","fare":"13.4","fareHoliday":"22.1"},{"seq":"27","stop":"22","fare":"13.4","fareHoliday":"22.1"},{"seq":"28","stop":"23","fare":"13.4","fareHoliday":"22.1"},{"seq":"29","stop":"24","fare":"13.4","fareHoliday":"22.1"},{"seq":"30","stop":"25","fare":"13.4","fareHoliday":"22.1"},{"seq":"31","stop":"26","fare":"13.4","fareHoliday":"22.1"},{"seq":"32","stop":"27","fare":"13.4","fareHoliday":"22.1"},{"seq":"33","stop":"28","fare":"7.3","fareHoliday":"15.0"},{"seq":"34","stop":"246","fare":"7.3","fareHoliday":"15.0"},{"seq":"35","stop":"247","fare":"7.3","fareHoliday":"15.0"},{"seq":"36","stop":"248","fare":"7.3","fareHoliday":"15.0"},{"seq":"37","stop":"249","fare":"5.6","fareHoliday":"8.1"},{"seq":"38","stop":"250","fare":"5.6","fareHoliday":"8.1"},{"seq":"39","stop":"251","fare":"5.6","fareHoliday":"8.1"},{"seq":"40","stop":"252","fare":"5.6","fareHoliday":"8.1"},{"seq":"41","stop":"253","fare":"5.6","fareHoliday":"8.1"},{"seq":"42","stop":"254","fare":"5.6","fareHoliday":"8.1"},{"seq":"43","stop":"255","fare":"5.6","fareHoliday":"8.1"},{"seq":"44","stop":"256","fare":"5.6","fareHoliday":"8.1"},{"seq":"45","stop":"257","fare":"5.6","fareHoliday":"8.1"},{"seq":"46","stop":"258","fare":"5.6","fareHoliday":"8.1"},{"seq":"47","stop":"259","fare":"4.4","fareHoliday":"6.7"},{"seq":"48","stop":"260","fare":"4.4","fareHoliday":"6.7"},{"seq":"49","stop":"261","fare":"4.4","fareHoliday":"6.7"},{"seq":"50","stop":"262","fare":"4.4","fareHoliday":"6.7"},{"seq":"51","stop":"263","fare":"4.4","fareHoliday":"6.7"},{"seq":"52","stop":"264","fare":"4.4","fareHoliday":"6.7"},{"seq":"53","stop":"265","fare":"4.4","fareHoliday":"6.7"},{"seq":"54","stop":"56","fare":"4.4","fareHoliday":"6.7"},{"seq":"55","stop":"266","fare":"4.4","fareHoliday":"6.7"},{"seq":"56","stop":"57","fare":"4.4","fareHoliday":"6.7"},{"seq":"57","stop":"2","fare":"4.4","fareHoliday":"6.7"},{"seq":"58","stop":"3","fare":"4.4","fareHoliday":"6.7"},{"seq":"59","stop":"4","fare":"4.4","fareHoliday":"6.7"},{"seq":"60","stop":"5","fare":"4.4","fareHoliday":"6.7"},{"seq":"61","stop":"305","fare":"0.0","fareHoliday":"0.0"}]}},"B2":{"38":{"orig_en":"Shenzhen Bay Port","dest_en":"Yuen Long MTR Station","orig_tc":"深圳灣口岸","dest_tc":"元朗港鐵站","service_type":"Normal","stops":[{"seq":"1","stop":"152","fare":"15.8","fareHoliday":"15.8"},{"seq":"2","stop":"196","fare":"15.8","fareHoliday":"15.8"},{"seq":"3","stop":"153","fare":"15.8","fareHoliday":"15.8"},{"seq":"4","stop":"154","fare":"15.8","fareHoliday":"15.8"},{"seq":"5","stop":"147","fare":"15.8","fareHoliday":"15.8"},{"seq":"6","stop":"146","fare":"15.8","fareHoliday":"15.8"},{"seq":"7","stop":"145","fare":"4.6","fareHoliday":"4.6"},{"seq":"8","stop":"144","fare":"4.6","fareHoliday":"4.6"},{"seq":"9","stop":"143","fare":"4.6","fareHoliday":"4.6"},{"seq":"10","stop":"155","fare":"4.6","fareHoliday":"4.6"},{"seq":"11","stop":"156","fare":"4.6","fareHoliday":"4.6"},{"seq":"12","stop":"157","fare":"4.6","fareHoliday":"4.6"},{"seq":"13","stop":"158","fare":"4.6","fareHoliday":"4.6"},{"seq":"14","stop":"159","fare":"4.6","fareHoliday":"4.6"},{"seq":"15","stop":"160","fare":"4.6","fareHoliday":"4.6"},{"seq":"16","stop":"134","fare":"0.0","fareHoliday":"0.0"}]},"37":{"orig_en":"Yuen Long MTR Station","dest_en":"Shenzhen Bay Port","orig_tc":"元朗港鐵站","dest_tc":"深圳灣口岸","service_type":"Normal","stops":[{"seq":"1","stop":"161","fare":"15.8","fareHoliday":"15.8"},{"seq":"2","stop":"135","fare":"15.8","fareHoliday":"15.8"},{"seq":"3","stop":"136","fare":"15.8","fareHoliday":"15.8"},{"seq":"4","stop":"137","fare":"15.8","fareHoliday":"15.8"},{"seq":"5","stop":"138","fare":"15.8","fareHoliday":"15.8"},{"seq":"6","stop":"139","fare":"15.8","fareHoliday":"15.8"},{"seq":"7","stop":"140","fare":"15.8","fareHoliday":"15.8"},{"seq":"8","stop":"141","fare":"15.8","fareHoliday":"15.8"},{"seq":"9","stop":"142","fare":"15.8","fareHoliday":"15.8"},{"seq":"10","stop":"197","fare":"15.8","fareHoliday":"15.8"},{"seq":"11","stop":"199","fare":"15.8","fareHoliday":"15.8"},{"seq":"12","stop":"302","fare":"15.8","fareHoliday":"15.8"},{"seq":"13","stop":"200","fare":"11.3","fareHoliday":"11.3"},{"seq":"14","stop":"201","fare":"11.3","fareHoliday":"11.3"},{"seq":"15","stop":"195","fare":"11.3","fareHoliday":"11.3"},{"seq":"16","stop":"148","fare":"11.3","fareHoliday":"11.3"},{"seq":"17","stop":"149","fare":"11.3","fareHoliday":"11.3"},{"seq":"18","stop":"150","fare":"11.3","fareHoliday":"11.3"},{"seq":"19","stop":"151","fare":"11.3","fareHoliday":"11.3"},{"seq":"20","stop":"152","fare":"0.0","fareHoliday":"0.0"}]}},"B2P":{"33":{"orig_en":"Tin Shui Wai (Tin Tsz Estate)","dest_en":"Shenzhen Bay Port","orig_tc":"天水圍 (天慈邨)","dest_tc":"深圳灣口岸","service_type":"Normal","stops":[{"seq":"1","stop":"203","fare":"11.3","fareHoliday":"11.3"},{"seq":"2","stop":"163","fare":"11.3","fareHoliday":"11.3"},{"seq":"3","stop":"164","fare":"11.3","fareHoliday":"11.3"},{"seq":"4","stop":"165","fare":"11.3","fareHoliday":"11.3"},{"seq":"5","stop":"205","fare":"11.3","fareHoliday":"11.3"},{"seq":"6","stop":"206","fare":"11.3","fareHoliday":"11.3"},{"seq":"7","stop":"168","fare":"11.3","fareHoliday":"11.3"},{"seq":"8","stop":"169","fare":"11.3","fareHoliday":"11.3"},{"seq":"9","stop":"207","fare":"11.3","fareHoliday":"11.3"},{"seq":"10","stop":"152","fare":"0.0","fareHoliday":"0.0"}]},"34":{"orig_en":"Shenzhen Bay Port","dest_en":"Tin Shui Wai (Tin Tsz Estate)","orig_tc":"深圳灣口岸","dest_tc":"天水圍 (天慈邨)","service_type":"Normal","stops":[{"seq":"1","stop":"152","fare":"11.3","fareHoliday":"11.3"},{"seq":"2","stop":"170","fare":"4.6","fareHoliday":"4.6"},{"seq":"3","stop":"171","fare":"4.6","fareHoliday":"4.6"},{"seq":"4","stop":"172","fare":"4.6","fareHoliday":"4.6"},{"seq":"5","stop":"167","fare":"4.6","fareHoliday":"4.6"},{"seq":"6","stop":"166","fare":"4.6","fareHoliday":"4.6"},{"seq":"7","stop":"173","fare":"4.6","fareHoliday":"4.6"},{"seq":"8","stop":"174","fare":"4.6","fareHoliday":"4.6"},{"seq":"9","stop":"175","fare":"4.6","fareHoliday":"4.6"},{"seq":"10","stop":"162","fare":"0.0","fareHoliday":"0.0"}]}},"B2X":{"36":{"orig_en":"Shenzhen Bay Port","dest_en":"Tin Shui Wai (Tin Yiu Estate)","orig_tc":"深圳灣口岸","dest_tc":"天水圍 (天耀邨)","service_type":"Normal","stops":[{"seq":"1","stop":"152","fare":"11.3","fareHoliday":"11.3"},{"seq":"2","stop":"170","fare":"4.6","fareHoliday":"4.6"},{"seq":"3","stop":"176","fare":"0.0","fareHoliday":"0.0"}]},"35":{"orig_en":"Tin Shui Wai (Tin Yiu Estate)","dest_en":"Shenzhen Bay Port","orig_tc":"天水圍 (天耀邨)","dest_tc":"深圳灣口岸","service_type":"Normal","stops":[{"seq":"1","stop":"176","fare":"11.3","fareHoliday":"11.3"},{"seq":"2","stop":"169","fare":"11.3","fareHoliday":"11.3"},{"seq":"3","stop":"207","fare":"11.3","fareHoliday":"11.3"},{"seq":"4","stop":"152","fare":"0.0","fareHoliday":"0.0"}]}},"B4":{"87":{"orig_en":"HZMB Hong Kong Port","dest_en":"Airport (Passenger Terminal Building) (Circular)","orig_tc":"大橋香港口岸","dest_tc":"機場 (客運大樓) (循環線)","service_type":"Normal","stops":[{"seq":"1","stop":"307","fare":"9.8","fareHoliday":"9.8"},{"seq":"2","stop":"117","fare":"9.8","fareHoliday":"9.8"},{"seq":"3","stop":"118","fare":"9.8","fareHoliday":"9.8"},{"seq":"4","stop":"120","fare":"9.8","fareHoliday":"9.8"},{"seq":"5","stop":"335","fare":"9.8","fareHoliday":"9.8"},{"seq":"6","stop":"308","fare":"9.8","fareHoliday":"9.8"},{"seq":"7","stop":"313","fare":"0.0","fareHoliday":"0.0"}]}},"B6":{"88":{"orig_en":"HZMB Hong Kong Port","dest_en":"Mun Tung Estate","orig_tc":"大橋香港口岸","dest_tc":"滿東邨","service_type":"Normal","stops":[{"seq":"1","stop":"307","fare":"9.8","fareHoliday":"9.8"},{"seq":"2","stop":"78","fare":"9.8","fareHoliday":"9.8"},{"seq":"3","stop":"79","fare":"5.3","fareHoliday":"5.3"},{"seq":"4","stop":"81","fare":"5.3","fareHoliday":"5.3"},{"seq":"5","stop":"310","fare":"0.0","fareHoliday":"0.0"}]},"89":{"orig_en":"Mun Tung Estate","dest_en":"HZMB Hong Kong Port","orig_tc":"滿東邨","dest_tc":"大橋香港口岸","service_type":"Normal","stops":[{"seq":"1","stop":"309","fare":"9.8","fareHoliday":"9.8"},{"seq":"2","stop":"103","fare":"9.8","fareHoliday":"9.8"},{"seq":"3","stop":"306","fare":"9.8","fareHoliday":"9.8"},{"seq":"4","stop":"77","fare":"9.8","fareHoliday":"9.8"},{"seq":"5","stop":"317","fare":"9.8","fareHoliday":"9.8"},{"seq":"6","stop":"308","fare":"9.8","fareHoliday":"9.8"},{"seq":"7","stop":"313","fare":"0.0","fareHoliday":"0.0"}]}},"B6S":{"111":{"orig_en":"Mun Tung Estate","dest_en":"HZMB Hong Kong Port","orig_tc":"滿東邨","dest_tc":"大橋香港口岸","service_type":"Special","stops":[{"seq":"1","stop":"309","fare":"9.8","fareHoliday":"0.0"},{"seq":"2","stop":"103","fare":"9.8","fareHoliday":"0.0"},{"seq":"3","stop":"306","fare":"9.8","fareHoliday":"0.0"},{"seq":"4","stop":"77","fare":"9.8","fareHoliday":"0.0"},{"seq":"5","stop":"316","fare":"9.8","fareHoliday":"0.0"},{"seq":"6","stop":"308","fare":"9.8","fareHoliday":"0.0"},{"seq":"7","stop":"313","fare":"0.0","fareHoliday":"0.0"}]}},"N1":{"40":{"orig_en":"Mui Wo Ferry Pier","dest_en":"Tai O","orig_tc":"梅窩碼頭","dest_tc":"大澳","service_type":"Normal","stops":[{"seq":"1","stop":"1","fare":"19.2","fareHoliday":"32.8"},{"seq":"2","stop":"6","fare":"19.2","fareHoliday":"32.8"},{"seq":"3","stop":"7","fare":"19.2","fareHoliday":"32.8"},{"seq":"4","stop":"8","fare":"19.2","fareHoliday":"32.8"},{"seq":"5","stop":"9","fare":"19.2","fareHoliday":"32.8"},{"seq":"6","stop":"10","fare":"19.2","fareHoliday":"32.8"},{"seq":"7","stop":"11","fare":"16.8","fareHoliday":"29.7"},{"seq":"8","stop":"12","fare":"16.8","fareHoliday":"29.7"},{"seq":"9","stop":"13","fare":"16.8","fareHoliday":"29.7"},{"seq":"10","stop":"14","fare":"16.8","fareHoliday":"29.7"},{"seq":"11","stop":"15","fare":"16.8","fareHoliday":"29.7"},{"seq":"12","stop":"16","fare":"13.8","fareHoliday":"24.2"},{"seq":"13","stop":"17","fare":"13.8","fareHoliday":"24.2"},{"seq":"14","stop":"18","fare":"13.8","fareHoliday":"24.2"},{"seq":"15","stop":"83","fare":"13.8","fareHoliday":"24.2"},{"seq":"16","stop":"19","fare":"13.8","fareHoliday":"24.2"},{"seq":"17","stop":"20","fare":"13.8","fareHoliday":"24.2"},{"seq":"18","stop":"21","fare":"13.8","fareHoliday":"24.2"},{"seq":"19","stop":"22","fare":"13.8","fareHoliday":"24.2"},{"seq":"20","stop":"23","fare":"13.8","fareHoliday":"24.2"},{"seq":"21","stop":"24","fare":"13.8","fareHoliday":"24.2"},{"seq":"22","stop":"25","fare":"13.8","fareHoliday":"24.2"},{"seq":"23","stop":"26","fare":"13.8","fareHoliday":"24.2"},{"seq":"24","stop":"27","fare":"9.6","fareHoliday":"19.6"},{"seq":"25","stop":"28","fare":"9.6","fareHoliday":"19.6"},{"seq":"26","stop":"31","fare":"9.6","fareHoliday":"19.6"},{"seq":"27","stop":"178","fare":"9.6","fareHoliday":"19.6"},{"seq":"28","stop":"33","fare":"9.6","fareHoliday":"19.6"},{"seq":"29","stop":"34","fare":"9.6","fareHoliday":"19.6"},{"seq":"30","stop":"35","fare":"9.6","fareHoliday":"19.6"},{"seq":"31","stop":"36","fare":"9.6","fareHoliday":"19.6"},{"seq":"32","stop":"37","fare":"9.6","fareHoliday":"19.6"},{"seq":"33","stop":"38","fare":"9.6","fareHoliday":"19.6"},{"seq":"34","stop":"39","fare":"7.2","fareHoliday":"11.7"},{"seq":"35","stop":"41","fare":"7.2","fareHoliday":"11.7"},{"seq":"36","stop":"42","fare":"7.2","fareHoliday":"11.7"},{"seq":"37","stop":"58","fare":"3.2","fareHoliday":"8.0"},{"seq":"38","stop":"44","fare":"3.2","fareHoliday":"8.0"},{"seq":"39","stop":"45","fare":"3.2","fareHoliday":"8.0"},{"seq":"40","stop":"46","fare":"3.2","fareHoliday":"8.0"},{"seq":"41","stop":"47","fare":"3.2","fareHoliday":"8.0"},{"seq":"42","stop":"48","fare":"3.2","fareHoliday":"8.0"},{"seq":"43","stop":"49","fare":"3.2","fareHoliday":"8.0"},{"seq":"44","stop":"84","fare":"3.2","fareHoliday":"8.0"},{"seq":"45","stop":"51","fare":"3.2","fareHoliday":"8.0"},{"seq":"46","stop":"52","fare":"3.2","fareHoliday":"8.0"},{"seq":"47","stop":"53","fare":"3.2","fareHoliday":"8.0"},{"seq":"48","stop":"54","fare":"3.2","fareHoliday":"8.0"},{"seq":"49","stop":"55","fare":"0.0","fareHoliday":"0.0"}]}},"N35":{"93":{"orig_en":"HZMB Hong Kong Port","dest_en":"Mui Wo Ferry Pier","orig_tc":"大橋香港口岸","dest_tc":"梅窩碼頭","service_type":"Normal","stops":[{"seq":"1","stop":"307","fare":"34.2","fareHoliday":"47.9"},{"seq":"2","stop":"117","fare":"25.1","fareHoliday":"38.7"},{"seq":"3","stop":"118","fare":"25.1","fareHoliday":"38.7"},{"seq":"4","stop":"120","fare":"25.1","fareHoliday":"38.7"},{"seq":"5","stop":"274","fare":"25.1","fareHoliday":"38.7"},{"seq":"6","stop":"187","fare":"25.1","fareHoliday":"38.7"},{"seq":"7","stop":"126","fare":"25.1","fareHoliday":"38.7"},{"seq":"8","stop":"122","fare":"25.1","fareHoliday":"38.7"},{"seq":"9","stop":"276","fare":"25.1","fareHoliday":"38.7"},{"seq":"10","stop":"78","fare":"17.9","fareHoliday":"28.4"},{"seq":"11","stop":"79","fare":"17.9","fareHoliday":"28.4"},{"seq":"12","stop":"80","fare":"17.9","fareHoliday":"28.4"},{"seq":"13","stop":"81","fare":"17.9","fareHoliday":"28.4"},{"seq":"14","stop":"185","fare":"17.9","fareHoliday":"28.4"},{"seq":"15","stop":"76","fare":"17.9","fareHoliday":"28.4"},{"seq":"16","stop":"90","fare":"17.9","fareHoliday":"28.4"},{"seq":"17","stop":"94","fare":"17.9","fareHoliday":"28.4"},{"seq":"18","stop":"279","fare":"17.9","fareHoliday":"28.4"},{"seq":"19","stop":"280","fare":"17.9","fareHoliday":"28.4"},{"seq":"20","stop":"282","fare":"17.9","fareHoliday":"28.4"},{"seq":"21","stop":"283","fare":"17.9","fareHoliday":"28.4"},{"seq":"22","stop":"284","fare":"17.9","fareHoliday":"28.4"},{"seq":"23","stop":"286","fare":"17.9","fareHoliday":"28.4"},{"seq":"24","stop":"287","fare":"17.9","fareHoliday":"28.4"},{"seq":"25","stop":"288","fare":"17.9","fareHoliday":"28.4"},{"seq":"26","stop":"273","fare":"17.9","fareHoliday":"28.4"},{"seq":"27","stop":"83","fare":"17.9","fareHoliday":"28.4"},{"seq":"28","stop":"19","fare":"17.9","fareHoliday":"28.4"},{"seq":"29","stop":"20","fare":"17.9","fareHoliday":"28.4"},{"seq":"30","stop":"21","fare":"17.9","fareHoliday":"28.4"},{"seq":"31","stop":"22","fare":"17.9","fareHoliday":"28.4"},{"seq":"32","stop":"23","fare":"17.9","fareHoliday":"28.4"},{"seq":"33","stop":"24","fare":"17.9","fareHoliday":"28.4"},{"seq":"34","stop":"25","fare":"17.9","fareHoliday":"28.4"},{"seq":"35","stop":"26","fare":"17.9","fareHoliday":"28.4"},{"seq":"36","stop":"27","fare":"17.9","fareHoliday":"28.4"},{"seq":"37","stop":"28","fare":"10.1","fareHoliday":"20.6"},{"seq":"38","stop":"246","fare":"10.1","fareHoliday":"20.6"},{"seq":"39","stop":"247","fare":"10.1","fareHoliday":"20.6"},{"seq":"40","stop":"248","fare":"10.1","fareHoliday":"20.6"},{"seq":"41","stop":"249","fare":"7.5","fareHoliday":"12.1"},{"seq":"42","stop":"250","fare":"7.5","fareHoliday":"12.1"},{"seq":"43","stop":"251","fare":"7.5","fareHoliday":"12.1"},{"seq":"44","stop":"252","fare":"7.5","fareHoliday":"12.1"},{"seq":"45","stop":"253","fare":"7.5","fareHoliday":"12.1"},{"seq":"46","stop":"254","fare":"7.5","fareHoliday":"12.1"},{"seq":"47","stop":"255","fare":"7.5","fareHoliday":"12.1"},{"seq":"48","stop":"256","fare":"7.5","fareHoliday":"12.1"},{"seq":"49","stop":"257","fare":"7.5","fareHoliday":"12.1"},{"seq":"50","stop":"258","fare":"7.5","fareHoliday":"12.1"},{"seq":"51","stop":"259","fare":"6.3","fareHoliday":"9.1"},{"seq":"52","stop":"260","fare":"6.3","fareHoliday":"9.1"},{"seq":"53","stop":"261","fare":"6.3","fareHoliday":"9.1"},{"seq":"54","stop":"262","fare":"6.3","fareHoliday":"9.1"},{"seq":"55","stop":"263","fare":"6.3","fareHoliday":"9.1"},{"seq":"56","stop":"264","fare":"6.3","fareHoliday":"9.1"},{"seq":"57","stop":"265","fare":"6.3","fareHoliday":"9.1"},{"seq":"58","stop":"56","fare":"6.3","fareHoliday":"9.1"},{"seq":"59","stop":"266","fare":"6.3","fareHoliday":"9.1"},{"seq":"60","stop":"57","fare":"6.3","fareHoliday":"9.1"},{"seq":"61","stop":"305","fare":"0.0","fareHoliday":"0.0"}]},"92":{"orig_en":"Mui Wo Ferry Pier","dest_en":"HZMB Hong Kong Port","orig_tc":"梅窩碼頭","dest_tc":"大橋香港口岸","service_type":"Normal","stops":[{"seq":"1","stop":"1","fare":"34.2","fareHoliday":"47.9"},{"seq":"2","stop":"6","fare":"34.2","fareHoliday":"47.9"},{"seq":"3","stop":"7","fare":"34.2","fareHoliday":"47.9"},{"seq":"4","stop":"8","fare":"34.2","fareHoliday":"47.9"},{"seq":"5","stop":"9","fare":"34.2","fareHoliday":"47.9"},{"seq":"6","stop":"10","fare":"34.2","fareHoliday":"47.9"},{"seq":"7","stop":"11","fare":"29.9","fareHoliday":"41.5"},{"seq":"8","stop":"12","fare":"29.9","fareHoliday":"41.5"},{"seq":"9","stop":"13","fare":"29.9","fareHoliday":"41.5"},{"seq":"10","stop":"14","fare":"29.9","fareHoliday":"41.5"},{"seq":"11","stop":"15","fare":"29.9","fareHoliday":"41.5"},{"seq":"12","stop":"16","fare":"29.9","fareHoliday":"41.5"},{"seq":"13","stop":"17","fare":"29.9","fareHoliday":"41.5"},{"seq":"14","stop":"18","fare":"29.9","fareHoliday":"41.5"},{"seq":"15","stop":"83","fare":"29.9","fareHoliday":"41.5"},{"seq":"16","stop":"19","fare":"29.9","fareHoliday":"41.5"},{"seq":"17","stop":"20","fare":"29.9","fareHoliday":"41.5"},{"seq":"18","stop":"21","fare":"29.9","fareHoliday":"41.5"},{"seq":"19","stop":"22","fare":"29.9","fareHoliday":"41.5"},{"seq":"20","stop":"23","fare":"29.9","fareHoliday":"41.5"},{"seq":"21","stop":"24","fare":"29.9","fareHoliday":"41.5"},{"seq":"22","stop":"25","fare":"29.9","fareHoliday":"41.5"},{"seq":"23","stop":"26","fare":"29.9","fareHoliday":"41.5"},{"seq":"24","stop":"27","fare":"29.9","fareHoliday":"41.5"},{"seq":"25","stop":"28","fare":"24.8","fareHoliday":"35.1"},{"seq":"26","stop":"246","fare":"24.8","fareHoliday":"35.1"},{"seq":"27","stop":"247","fare":"24.8","fareHoliday":"35.1"},{"seq":"28","stop":"248","fare":"24.8","fareHoliday":"35.1"},{"seq":"29","stop":"249","fare":"24.8","fareHoliday":"35.1"},{"seq":"30","stop":"250","fare":"24.8","fareHoliday":"35.1"},{"seq":"31","stop":"251","fare":"24.8","fareHoliday":"35.1"},{"seq":"32","stop":"252","fare":"24.8","fareHoliday":"35.1"},{"seq":"33","stop":"253","fare":"24.8","fareHoliday":"35.1"},{"seq":"34","stop":"254","fare":"24.8","fareHoliday":"35.1"},{"seq":"35","stop":"255","fare":"24.8","fareHoliday":"35.1"},{"seq":"36","stop":"179","fare":"24.8","fareHoliday":"35.1"},{"seq":"37","stop":"64","fare":"24.8","fareHoliday":"35.1"},{"seq":"38","stop":"65","fare":"24.8","fareHoliday":"35.1"},{"seq":"39","stop":"66","fare":"24.8","fareHoliday":"35.1"},{"seq":"40","stop":"67","fare":"24.8","fareHoliday":"35.1"},{"seq":"41","stop":"68","fare":"19.2","fareHoliday":"24.5"},{"seq":"42","stop":"69","fare":"19.2","fareHoliday":"24.5"},{"seq":"43","stop":"70","fare":"19.2","fareHoliday":"24.5"},{"seq":"44","stop":"71","fare":"19.2","fareHoliday":"24.5"},{"seq":"45","stop":"72","fare":"19.2","fareHoliday":"24.5"},{"seq":"46","stop":"73","fare":"19.2","fareHoliday":"24.5"},{"seq":"47","stop":"74","fare":"19.2","fareHoliday":"24.5"},{"seq":"48","stop":"185","fare":"9.0","fareHoliday":"9.1"},{"seq":"49","stop":"76","fare":"9.0","fareHoliday":"9.1"},{"seq":"50","stop":"77","fare":"9.0","fareHoliday":"9.1"},{"seq":"51","stop":"121","fare":"9.0","fareHoliday":"9.1"},{"seq":"52","stop":"122","fare":"9.0","fareHoliday":"9.1"},{"seq":"53","stop":"124","fare":"9.0","fareHoliday":"9.1"},{"seq":"54","stop":"125","fare":"9.0","fareHoliday":"9.1"},{"seq":"55","stop":"115","fare":"9.0","fareHoliday":"9.1"},{"seq":"56","stop":"116","fare":"9.0","fareHoliday":"9.1"},{"seq":"57","stop":"117","fare":"9.0","fareHoliday":"9.1"},{"seq":"58","stop":"308","fare":"9.0","fareHoliday":"9.1"},{"seq":"59","stop":"313","fare":"0.0","fareHoliday":"0.0"}]}},"N37":{"86":{"orig_en":"Ying Tung Estate","dest_en":"Tung Chung Station Bus Terminus (Circular)","orig_tc":"迎東邨","dest_tc":"東涌站巴士總站 (循環線)","service_type":"Normal","stops":[{"seq":"1","stop":"297","fare":"5.4","fareHoliday":"5.4"},{"seq":"2","stop":"191","fare":"5.4","fareHoliday":"5.4"},{"seq":"3","stop":"298","fare":"5.4","fareHoliday":"5.4"},{"seq":"4","stop":"111","fare":"5.4","fareHoliday":"5.4"},{"seq":"5","stop":"112","fare":"5.4","fareHoliday":"5.4"},{"seq":"6","stop":"299","fare":"5.4","fareHoliday":"5.4"},{"seq":"7","stop":"78","fare":"5.4","fareHoliday":"5.4"},{"seq":"8","stop":"105","fare":"5.4","fareHoliday":"5.4"},{"seq":"9","stop":"107","fare":"5.4","fareHoliday":"5.4"},{"seq":"10","stop":"108","fare":"5.4","fareHoliday":"5.4"},{"seq":"11","stop":"186","fare":"5.4","fareHoliday":"5.4"},{"seq":"12","stop":"109","fare":"5.4","fareHoliday":"5.4"},{"seq":"13","stop":"194","fare":"5.4","fareHoliday":"5.4"},{"seq":"14","stop":"190","fare":"5.4","fareHoliday":"5.4"},{"seq":"15","stop":"193","fare":"0.0","fareHoliday":"0.0"}]}},"N38":{"45":{"orig_en":"Tung Chung Station Bus Terminus","dest_en":"Yat Tung Estate","orig_tc":"東涌站巴士總站","dest_tc":"逸東邨","service_type":"Normal","stops":[{"seq":"1","stop":"105","fare":"5.4","fareHoliday":"5.4"},{"seq":"2","stop":"81","fare":"5.4","fareHoliday":"5.4"},{"seq":"3","stop":"185","fare":"5.4","fareHoliday":"5.4"},{"seq":"4","stop":"88","fare":"5.4","fareHoliday":"5.4"},{"seq":"5","stop":"89","fare":"0.0","fareHoliday":"0.0"}]},"44":{"orig_en":"Yat Tung Estate","dest_en":"Tung Chung Station Bus Terminus","orig_tc":"逸東邨","dest_tc":"東涌站巴士總站","service_type":"Normal","stops":[{"seq":"1","stop":"289","fare":"5.4","fareHoliday":"5.4"},{"seq":"2","stop":"76","fare":"5.4","fareHoliday":"5.4"},{"seq":"3","stop":"77","fare":"5.4","fareHoliday":"5.4"},{"seq":"4","stop":"78","fare":"5.4","fareHoliday":"5.4"},{"seq":"5","stop":"105","fare":"0.0","fareHoliday":"0.0"}]}},"NB2":{"110":{"orig_en":"Shenzhen Bay Port","dest_en":"Yuen Long MTR Station (Circular)","orig_tc":"深圳灣口岸","dest_tc":"元朗港鐵站 (循環線)","service_type":"Special","stops":[{"seq":"1","stop":"152","fare":"21.5","fareHoliday":"21.5"},{"seq":"2","stop":"170","fare":"21.5","fareHoliday":"21.5"},{"seq":"3","stop":"134","fare":"21.5","fareHoliday":"21.5"},{"seq":"4","stop":"152","fare":"21.5","fareHoliday":"21.5"}]}},"X11R":{"108":{"orig_en":"Sheraton Hong Kong Tung Chung Hotel","dest_en":"Tai O","orig_tc":"東涌世茂喜來登酒店","dest_tc":"大澳","service_type":"Special","stops":[{"seq":"1","stop":"333","fare":"31.5","fareHoliday":"43.9"},{"seq":"2","stop":"77","fare":"31.5","fareHoliday":"43.9"},{"seq":"3","stop":"288","fare":"31.5","fareHoliday":"43.9"},{"seq":"4","stop":"26","fare":"31.5","fareHoliday":"43.9"},{"seq":"5","stop":"41","fare":"31.5","fareHoliday":"43.9"},{"seq":"6","stop":"55","fare":"31.5","fareHoliday":"43.9"}]},"109":{"orig_en":"Tai O","dest_en":"Sheraton Hong Kong Tung Chung Hotel","orig_tc":"大澳","dest_tc":"東涌世茂喜來登酒店","service_type":"Special","stops":[{"seq":"1","stop":"221","fare":"31.5","fareHoliday":"43.9"},{"seq":"2","stop":"235","fare":"31.5","fareHoliday":"43.9"},{"seq":"3","stop":"247","fare":"31.5","fareHoliday":"43.9"},{"seq":"4","stop":"65","fare":"31.5","fareHoliday":"43.9"},{"seq":"5","stop":"77","fare":"31.5","fareHoliday":"43.9"},{"seq":"6","stop":"78","fare":"31.5","fareHoliday":"43.9"},{"seq":"7","stop":"334","fare":"31.5","fareHoliday":"43.9"}]}},"XB2":{"114":{"orig_en":"Shenzhen Bay Port","dest_en":"Yuen Long MTR Station(Express)","orig_tc":"深圳灣口岸","dest_tc":"元朗港鐵站(特快)","service_type":"Normal","stops":[{"seq":"1","stop":"152","fare":"15.8","fareHoliday":"15.8"},{"seq":"2","stop":"157","fare":"15.8","fareHoliday":"15.8"},{"seq":"3","stop":"158","fare":"15.8","fareHoliday":"15.8"},{"seq":"4","stop":"159","fare":"15.8","fareHoliday":"15.8"},{"seq":"5","stop":"160","fare":"15.8","fareHoliday":"15.8"},{"seq":"6","stop":"134","fare":"0.0","fareHoliday":"0.0"}]},"113":{"orig_en":"Yuen Long MTR Station","dest_en":"Shenzhen Bay Port(Express)","orig_tc":"元朗港鐵站","dest_tc":"深圳灣口岸(特快)","service_type":"Normal","stops":[{"seq":"1","stop":"161","fare":"15.8","fareHoliday":"15.8"},{"seq":"2","stop":"135","fare":"15.8","fareHoliday":"15.8"},{"seq":"3","stop":"136","fare":"15.8","fareHoliday":"15.8"},{"seq":"4","stop":"137","fare":"15.8","fareHoliday":"15.8"},{"seq":"5","stop":"138","fare":"15.8","fareHoliday":"15.8"},{"seq":"6","stop":"139","fare":"15.8","fareHoliday":"15.8"},{"seq":"7","stop":"152","fare":"0.0","fareHoliday":"0.0"}]}}}